Workbook
Name GSPC: 'SP500'!$A$1:$B$24739

Sheet Customer Margin Balances
A1: Year-Month | B1: Debit Balances in Customers' Securities Margin Accounts | C1: Free Credit Balances in Customers' Cash Accounts | D1: Free Credit Balances in Customers' Securities Margin Accounts | G1: Date | H1: {=Customer_Margin_Balances[[#All],[Debit Balances in Customers'' Securities Margin Accounts]:[Free Credit Balances in Customers'' Securities Margin Accounts]]} -> Debit Balances in Customers' Securities Margin Accounts | I1: Free Credit Balances in Customers' Cash Accounts | J1: Free Credit Balances in Customers' Securities Margin Accounts | K1: Free Credit Balances | L1: US M2 | M1: Debit Balances : USM2 | N1: Retail Money Market Funds | O1: Free Credit Balances | P1: =N1 & " : USM2" -> Retail Money Market Funds : USM2 | Q1: =O1 & " : USM2" -> Free Credit Balances : USM2 | R1: Debit+Credit Balances : USM2 | S1: (USD million) | T1: ="S&P 500 FwdRtn" & " (" & Z2 & "M)" -> S&P 500 FwdRtn (21M) | U1: FwdRtn Predict (Debit+Credit) | V1: FwdRtn Predict (Debit) | W1: FwdRtn Predict (Credit) | AB1: Debit + Credit | AC1: Coef | AD1: Std Err | AE1: R-Sq | AH1: t-Stat | AI1: p-value | AK1: =R1 -> Debit+Credit Balances : USM2 | AL1: =T1 -> S&P 500 FwdRtn (21M) | AM1: =M1 -> Debit Balances : USM2 | AN1: =T1 -> S&P 500 FwdRtn (21M) | AO1: =Q1 -> Free Credit Balances : USM2 | AP1: =T1 -> S&P 500 FwdRtn (21M)
A2: 46173 | B2: 1415557 | C2: 206600 | D2: 217256 | G2: {=Customer_Margin_Balances[Year-Month]} -> 46173 | H2: 1415557 | I2: 206600 | J2: 217256 | K2: {=Customer_Margin_Balances[Free Credit Balances in Customers'' Cash Accounts] +Customer_Margin_Balances[Free Credit Balances in Customers'' Securities Margin Accounts]} -> 423856 | L2: {=VLOOKUP(OFFSET(G2,,,COUNT(G:G)), 'USM2(NS)'!A:B, 2) *1000} -> 22971700 | M2: {=OFFSET(H2,,,COUNT(H:H)) /_xlfn.ANCHORARRAY(L2)} -> 0.061621778 | N2: {=VLOOKUP(OFFSET(G2,,,COUNT(G:G)), MMF!A:B, 2) *1000} -> 2270500 | O2: {=_xlfn.ANCHORARRAY(K2)} -> 423856 | P2: {=_xlfn.ANCHORARRAY(N2) /_xlfn.ANCHORARRAY($L2)} -> 0.098839006 | Q2: {=_xlfn.ANCHORARRAY(O2) /_xlfn.ANCHORARRAY($L2)} -> 0.018451225 | R2: {=(_xlfn.ANCHORARRAY(M2) +_xlfn.ANCHORARRAY(Q2))} -> 0.080073003 | T2: {=IF(EOMONTH(--_xlfn.ANCHORARRAY(G2), $Z$2) >MAX('SP500'!A:A), NA(), INDEX('SP500'!B:B, MATCH(EOMONTH(--_xlfn.ANCHORARRAY(G2), $Z$2), 'SP500'!A:A, 1)) /INDEX('SP500'!B:B, MATCH(_xlfn.ANCHORARRAY(G2), 'SP500'!A:A, 1)) -1)} -> #N/A | U2: {=IF(_xlfn.ANCHORARRAY($G2) >$Z$5, AC2 *_xlfn.ANCHORARRAY(R2) +AC3, NA())} -> -0.34598011 | V2: {=IF(_xlfn.ANCHORARRAY($G2) >$Z$5, AC7 *_xlfn.ANCHORARRAY(M2) +AC8, NA())} -> -0.76119141 | W2: {=IF(_xlfn.ANCHORARRAY($G2) >$Z$5, AC12 *_xlfn.ANCHORARRAY(Q2) +AC13, NA())} -> 0.28028168 | Y2: Mth FwdRtn | Z2: 21 | AB2: Slope | AC2: {=_xlfn.LET(_xlpm.trainingSince, $Z$5, _xlpm.trainingUntil, $Z$6, _xlpm.dtCol,_xlfn.ANCHORARRAY( $G$2), _xlpm.original_y,_xlfn.ANCHORARRAY( $T$2), _xlpm.clean_y, _xlfn._xlws.FILTER(_xlpm.original_y, ISNUMBER(_xlpm.original_y) *(_xlpm.dtCol>_xlpm.trainingSince) *(_xlpm.dtCol<=_xlpm.trainingUntil)), _xlpm.original_x,_xlfn.ANCHORARRAY( $R$2), _xlpm.clean_x, _xlfn._xlws.FILTER(_xlpm.original_x, ISNUMBER(_xlpm.original_y) *(_xlpm.dtCol>_xlpm.trainingSince) *(_xlpm.dtCol<=_xlpm.trainingUntil)), TRANSPOSE(LINEST(_xlpm.clean_y, _xlpm.clean_x, TRUE, TRUE)))} -> -24.358639 | AD2: 3.0252035 | AE2: 0.53214688 | AF2: 64.833108 | AG2: 1.3777903 | AH2: {=AC2:AC3 /AD2:AD3} -> -8.0519009 | AI2: {=_xlfn.T.DIST.2T(ABS(_xlfn.ANCHORARRAY(AH2)), AF3)} -> 5.6357201e-11 | AK2: {=_xlfn._xlws.FILTER(_xlfn.ANCHORARRAY(R2), (_xlfn.ANCHORARRAY($G$2) >=$Z$5) *(_xlfn.ANCHORARRAY($G$2) <=$Z$6))} -> 0.053700457 | AL2: {=_xlfn._xlws.FILTER(_xlfn.ANCHORARRAY(T2), (_xlfn.ANCHORARRAY($G$2) >=$Z$5) *(_xlfn.ANCHORARRAY($G$2) <=$Z$6))} -> #N/A | AM2: {=_xlfn._xlws.FILTER(_xlfn.ANCHORARRAY(M2), (_xlfn.ANCHORARRAY($G$2) >=$Z$5) *(_xlfn.ANCHORARRAY($G$2) <=$Z$6))} -> 0.038324662 | AN2: {=_xlfn._xlws.FILTER(_xlfn.ANCHORARRAY(T2), (_xlfn.ANCHORARRAY($G$2) >=$Z$5) *(_xlfn.ANCHORARRAY($G$2) <=$Z$6))} -> #N/A | AO2: {=_xlfn._xlws.FILTER(_xlfn.ANCHORARRAY(Q2), (_xlfn.ANCHORARRAY($G$2) >=$Z$5) *(_xlfn.ANCHORARRAY($G$2) <=$Z$6))} -> 0.015375795 | AP2: {=_xlfn._xlws.FILTER(_xlfn.ANCHORARRAY(T2), (_xlfn.ANCHORARRAY($G$2) >=$Z$5) *(_xlfn.ANCHORARRAY($G$2) <=$Z$6))} -> #N/A
A3: 46142 | B3: 1304281 | C3: 217836 | D3: 215445 | G3: 46142 | H3: 1304281 | I3: 217836 | J3: 215445 | K3: 433281 | L3: 22936200 | M3: 0.05686561 | N3: 2252000 | O3: 433281 | P3: 0.098185401 | Q3: 0.018890706 | R3: 0.075756315 | T3: #N/A | U3: -0.24083148 | V3: -0.57247411 | W3: 0.27200777 | Y3: Train Wdw | Z3: 60 | AB3: Intercept | AC3: 1.6044892 | AD3: 0.16733104 | AE3: 0.14577839 | AF3: 57 | AG3: 1.2113263 | AH3: 9.5887126 | AI3: 1.7128582e-13 | AK3: 0.051942011 | AL3: 0.3419836 | AM3: 0.037711558 | AN3: 0.3419836 | AO3: 0.014230453 | AP3: 0.3419836
A4: 46112 | B4: 1220922 | C4: 221860 | D4: 205600 | G4: 46112 | H4: 1220922 | I4: 221860 | J4: 205600 | K4: 427460 | L4: 22815700 | M4: 0.053512362 | N4: 2291400 | O4: 427460 | P4: 0.10043084 | Q4: 0.018735345 | R4: 0.072247707 | T4: #N/A | U4: -0.15536655 | V4: -0.4394225 | W4: 0.27493268 | Y4: Predict Wdw | Z4: 24 | AF4: DF | AK4: 0.053035473 | AL4: 0.30543614 | AM4: 0.038515086 | AN4: 0.30543614 | AO4: 0.014520387 | AP4: 0.30543614
A5: 46081 | B5: 1253192 | C5: 205060 | D5: 200047 | G5: 46081 | H5: 1253192 | I5: 205060 | J5: 200047 | K5: 405107 | L5: 22531900 | M5: 0.055618567 | N5: 2263100 | O5: 405107 | P5: 0.10043982 | Q5: 0.017979265 | R5: 0.073597832 | T5: #N/A | U5: -0.18825377 | V5: -0.52299343 | W5: 0.28916706 | Y5: Train since | Z5: =EOMONTH(Z6, -Z3) -> 43738 | AK5: 0.053051161 | AL5: 0.19559453 | AM5: 0.038463132 | AN5: 0.19559453 | AO5: 0.014588028 | AP5: 0.19559453
A6: 46053 | B6: 1279042 | C6: 203700 | D6: 196911 | G6: 46053 | H6: 1279042 | I6: 203700 | J6: 196911 | K6: 400611 | L6: 22466200 | M6: 0.056931835 | N6: 2256000 | O6: 400611 | P6: 0.10041752 | Q6: 0.017831721 | R6: 0.074763556 | T6: #N/A | U6: -0.21664921 | V6: -0.57510184 | W6: 0.29194482 | Y6: Train until | Z6: =EOMONTH(TODAY(), -1 -Z2) -> 45565 | AB6: Debit | AC6: Coef | AD6: Std Err | AE6: R-Sq | AH6: t-Stat | AI6: p-value | AK6: 0.053003162 | AL6: 0.3034329 | AM6: 0.038659206 | AN6: 0.3034329 | AO6: 0.014343955 | AP6: 0.3034329
A7: 46022 | B7: 1225597 | C7: 211720 | D7: 199762 | G7: 46022 | H7: 1225597 | I7: 211720 | J7: 199762 | K7: 411482 | L7: 22503200 | M7: 0.054463232 | N7: 2250300 | O7: 411482 | P7: 0.099999111 | Q7: 0.018285488 | R7: 0.07274872 | T7: #N/A | U7: -0.16757055 | V7: -0.47715152 | W7: 0.28340193 | AB7: Slope | AC7: {=_xlfn.LET(_xlpm.trainingSince, $Z$5, _xlpm.trainingUntil, $Z$6, _xlpm.dtCol,_xlfn.ANCHORARRAY( $G$2), _xlpm.original_y,_xlfn.ANCHORARRAY( $T$2), _xlpm.clean_y, _xlfn._xlws.FILTER(_xlpm.original_y, ISNUMBER(_xlpm.original_y) *(_xlpm.dtCol>_xlpm.trainingSince) *(_xlpm.dtCol<=_xlpm.trainingUntil)), _xlpm.original_x,_xlfn.ANCHORARRAY( $M$2), _xlpm.clean_x, _xlfn._xlws.FILTER(_xlpm.original_x, ISNUMBER(_xlpm.original_y) *(_xlpm.dtCol>_xlpm.trainingSince) *(_xlpm.dtCol<=_xlpm.trainingUntil)), TRANSPOSE(LINEST(_xlpm.clean_y, _xlpm.clean_x, TRUE, TRUE)))} -> -39.678432 | AD7: 3.5388153 | AE7: 0.68804177 | AF7: 125.71677 | AG7: 1.7814204 | AH7: {=AC7:AC8 /AD7:AD8} -> -11.212349 | AI7: {=_xlfn.T.DIST.2T(ABS(_xlfn.ANCHORARRAY(AH7)), AF8)} -> 4.8057539e-16 | AK7: 0.05159488 | AL7: 0.37797002 | AM7: 0.036805399 | AN7: 0.37797002 | AO7: 0.01478948 | AP7: 0.37797002
A8: 45991 | B8: 1214321 | C8: 202131 | D8: 194418 | G8: 45991 | H8: 1214321 | I8: 202131 | J8: 194418 | K8: 396549 | L8: 22269200 | M8: 0.05452917 | N8: 2222200 | O8: 396549 | P8: 0.099788048 | Q8: 0.017807061 | R8: 0.072336231 | T8: #N/A | U8: -0.15752288 | V8: -0.47976786 | W8: 0.29240908 | AB8: Intercept | AC8: 1.6838641 | AD8: 0.12741491 | AE8: 0.11903827 | AF8: 57 | AG8: 0.80769625 | AH8: 13.215598 | AI8: 5.3169528e-19 | AK8: 0.052277275 | AL8: 0.30282525 | AM8: 0.03718258 | AN8: 0.30282525 | AO8: 0.015094695 | AP8: 0.30282525
A9: 45961 | B9: 1183654 | C9: 197923 | D9: 195376 | G9: 45961 | H9: 1183654 | I9: 197923 | J9: 195376 | K9: 393299 | L9: 22179000 | M9: 0.053368231 | N9: 2194600 | O9: 393299 | P9: 0.098949457 | Q9: 0.017732946 | R9: 0.071101177 | T9: #N/A | U9: -0.12743864 | V9: -0.43370361 | W9: 0.29380441 | AF9: DF | AK9: 0.050839158 | AL9: 0.34394171 | AM9: 0.035642777 | AN9: 0.34394171 | AO9: 0.015196381 | AP9: 0.34394171
A10: 45930 | B10: 1126494 | C10: 204106 | D10: 194884 | G10: 45930 | H10: 1126494 | I10: 204106 | J10: 194884 | K10: 398990 | L10: 22111600 | M10: 0.050945838 | N10: 2163400 | O10: 398990 | P10: 0.097840048 | Q10: 0.018044375 | R10: 0.068990213 | T10: #N/A | U10: -0.076018442 | V10: -0.33758686 | W10: 0.28794127 | AK10: 0.04847877 | AL10: 0.41161667 | AM10: 0.033629317 | AN10: 0.41161667 | AO10: 0.014849453 | AP10: 0.41161667
A11: 45900 | B11: 1059723 | C11: 188221 | D11: 181563 | G11: 45900 | H11: 1059723 | I11: 188221 | J11: 181563 | K11: 369784 | L11: 22033100 | M11: 0.048096863 | N11: 2158200 | O11: 369784 | P11: 0.097952626 | Q11: 0.016783113 | R11: 0.064879976 | T11: #N/A | U11: 0.024101342 | V11: -0.224544 | W11: 0.3116865 | AB11: Credit | AC11: Coef | AD11: Std Err | AE11: R-Sq | AH11: t-Stat | AI11: p-value | AK11: 0.048281549 | AL11: 0.40224282 | AM11: 0.033518309 | AN11: 0.40224282 | AO11: 0.014763239 | AP11: 0.40224282
A12: 45869 | B12: 1022548 | C12: 194712 | D12: 186672 | G12: 45869 | H12: 1022548 | I12: 194712 | J12: 186672 | K12: 381384 | L12: 21965600 | M12: 0.046552245 | N12: 2127800 | O12: 381384 | P12: 0.096869651 | Q12: 0.017362785 | R12: 0.063915031 | T12: #N/A | U12: 0.047606095 | V12: -0.16325598 | W12: 0.30077325 | AB12: Slope | AC12: {=_xlfn.LET(_xlpm.trainingSince, $Z$5, _xlpm.trainingUntil, $Z$6, _xlpm.dtCol,_xlfn.ANCHORARRAY( $G$2), _xlpm.original_y,_xlfn.ANCHORARRAY( $T$2), _xlpm.clean_y, _xlfn._xlws.FILTER(_xlpm.original_y, ISNUMBER(_xlpm.original_y) *(_xlpm.dtCol>_xlpm.trainingSince) *(_xlpm.dtCol<=_xlpm.trainingUntil)), _xlpm.original_x,_xlfn.ANCHORARRAY( Q2), _xlpm.clean_x, _xlfn._xlws.FILTER(_xlpm.original_x, ISNUMBER(_xlpm.original_y) *(_xlpm.dtCol>_xlpm.trainingSince) *(_xlpm.dtCol<=_xlpm.trainingUntil)), TRANSPOSE(LINEST(_xlpm.clean_y, _xlpm.clean_x, TRUE, TRUE)))} -> -18.826564 | AD12: 8.1904724 | AE12: 0.0848303 | AF12: 5.2835306 | AG12: 0.21963554 | AH12: {=AC12:AC13 /AD12:AD13} -> -2.2985932 | AI12: {=_xlfn.T.DIST.2T(ABS(_xlfn.ANCHORARRAY(AH12)), AF13)} -> 0.025215735 | AK12: 0.047151525 | AL12: 0.41430449 | AM12: 0.031849362 | AN12: 0.41430449 | AO12: 0.015302163 | AP12: 0.41430449
A13: 45838 | B13: 1007961 | C13: 200573 | D13: 185584 | G13: 45838 | H13: 1007961 | I13: 200573 | J13: 185584 | K13: 386157 | L13: 21908000 | M13: 0.04600881 | N13: 2114300 | O13: 386157 | P13: 0.096508125 | Q13: 0.017626301 | R13: 0.06363511 | T13: #N/A | U13: 0.054424572 | V13: -0.1416933 | W13: 0.29581216 | AB13: Intercept | AC13: 0.62765484 | AD13: 0.15962495 | AE13: 0.20388684 | AF13: 57 | AG13: 2.3694811 | AH13: 3.9320598 | AI13: 0.00023070713 | AK13: 0.045477137 | AL13: 0.5116101 | AM13: 0.030726177 | AN13: 0.5116101 | AO13: 0.01475096 | AP13: 0.5116101
A14: 45808 | B14: 920960 | C14: 187685 | D14: 176698 | G14: 45808 | H14: 920960 | I14: 187685 | J14: 176698 | K14: 364383 | L14: 21753800 | M14: 0.042335592 | N14: 2098900 | O14: 364383 | P14: 0.096484292 | Q14: 0.016750315 | R14: 0.059085907 | T14: #N/A | U14: 0.16523698 | V14: 0.0040542138 | W14: 0.31230397 | AF14: DF | AK14: 0.047151859 | AL14: 0.44703315 | AM14: 0.032875229 | AN14: 0.44703315 | AO14: 0.01427663 | AP14: 0.44703315
A15: 45777 | B15: 850558 | C15: 187958 | D15: 175824 | G15: 45777 | H15: 850558 | I15: 187958 | J15: 175824 | K15: 363782 | L15: 21896800 | M15: 0.038843941 | N15: 2087500 | O15: 363782 | P15: 0.095333565 | Q15: 0.016613478 | R15: 0.055457418 | T15: #N/A | U15: 0.25362202 | V15: 0.14259746 | W15: 0.31488014 | AK15: 0.048868138 | AL15: 0.31147641 | AM15: 0.033250751 | AN15: 0.31147641 | AO15: 0.015617386 | AP15: 0.31147641
A16: 45747 | B16: 880316 | C16: 189855 | D16: 176161 | G16: 45747 | H16: 880316 | I16: 189855 | J16: 176161 | K16: 366016 | L16: 21819100 | M16: 0.040346119 | N16: 2110300 | O16: 366016 | P16: 0.096718013 | Q16: 0.016775027 | R16: 0.057121146 | T16: #N/A | U16: 0.21309588 | V16: 0.08299339 | W16: 0.31183872 | AK16: 0.049758762 | AL16: 0.21357783 | AM16: 0.034206724 | AN16: 0.21357783 | AO16: 0.015552038 | AP16: 0.21357783
A17: 45716 | B17: 918144 | C17: 183278 | D17: 176051 | G17: 45716 | H17: 918144 | I17: 183278 | J17: 176051 | K17: 359329 | L17: 21531900 | M17: 0.042641105 | N17: 2062100 | O17: 359329 | P17: 0.095769533 | Q17: 0.016688216 | R17: 0.059329321 | T17: #N/A | U17: 0.15930775 | V17: -0.0080680492 | W17: 0.31347308 | AG17: in-sample | AK17: 0.048527521 | AL17: 0.26098226 | AM17: 0.032796915 | AN17: 0.26098226 | AO17: 0.015730606 | AP17: 0.26098226
A18: 45688 | B18: 937253 | C18: 178301 | D18: 166346 | G18: 45688 | H18: 937253 | I18: 178301 | J18: 166346 | K18: 344647 | L18: 21584400 | M18: 0.043422703 | N18: 2044800 | O18: 344647 | P18: 0.094735086 | Q18: 0.015967412 | R18: 0.059390115 | T18: #N/A | U18: 0.15782688 | V18: -0.039080666 | W18: 0.32704335 | AG18: Avg R-Sq | AH18: Latest | AK18: 0.046788091 | AL18: 0.42457944 | AM18: 0.031067694 | AN18: 0.42457944 | AO18: 0.015720397 | AP18: 0.42457944
A19: 45657 | B19: 899168 | C19: 181280 | D19: 175795 | G19: 45657 | H19: 899168 | I19: 181280 | J19: 175795 | K19: 357075 | L19: 21618400 | M19: 0.041592717 | N19: 2008200 | O19: 357075 | P19: 0.092893091 | Q19: 0.01651718 | R19: 0.058109897 | T19: #N/A | U19: 0.18901125 | V19: 0.033530314 | W19: 0.3166931 | AF19: D+C | AG19: {=AVERAGE(_xlfn.IFNA(_xlfn.ANCHORARRAY('R-Sq'!G3), ""))} -> 0.55526153 | AH19: =INDEX('R-Sq'!G:G, MATCH($Z$6, 'R-Sq'!$A:$A, 0)) -> #N/A | AK19: 0.045664213 | AL19: 0.44874896 | AM19: 0.030280549 | AN19: 0.44874896 | AO19: 0.015383664 | AP19: 0.44874896
A20: 45626 | B20: 890852 | C20: 170052 | D20: 167223 | G20: 45626 | H20: 890852 | I20: 170052 | J20: 167223 | K20: 337275 | L20: 21450500 | M20: 0.041530594 | N20: 1977200 | O20: 337275 | P20: 0.092175008 | Q20: 0.01572341 | R20: 0.057254003 | T20: #N/A | U20: 0.20985965 | V20: 0.035995282 | W20: 0.33163707 | AF20: D | AG20: {=AVERAGE(_xlfn.IFNA(_xlfn.ANCHORARRAY('R-Sq'!H3), ""))} -> 0.58364095 | AH20: =INDEX('R-Sq'!H:H, MATCH($Z$6, 'R-Sq'!$A:$A, 0)) -> #N/A | AK20: 0.046977121 | AL20: 0.43129377 | AM20: 0.030655739 | AN20: 0.43129377 | AO20: 0.016321382 | AP20: 0.43129377
A21: 45596 | B21: 815369 | C21: 173621 | D21: 164813 | G21: 45596 | H21: 815369 | I21: 173621 | J21: 164813 | K21: 338434 | L21: 21268300 | M21: 0.038337291 | N21: 1940600 | O21: 338434 | P21: 0.091243776 | Q21: 0.015912602 | R21: 0.054249893 | T21: #N/A | U21: 0.28303569 | V21: 0.16270054 | W21: 0.32807522 | AF21: C | AG21: {=AVERAGE(_xlfn.IFNA(_xlfn.ANCHORARRAY('R-Sq'!I3), ""))} -> 0.26028465 | AH21: =INDEX('R-Sq'!I:I, MATCH($Z$6, 'R-Sq'!$A:$A, 0)) -> #N/A | AK21: 0.046440609 | AL21: 0.51943378 | AM21: 0.029524258 | AN21: 0.51943378 | AO21: 0.016916351 | AP21: 0.51943378
A22: 45565 | B22: 813211 | C22: 167901 | D22: 158358 | G22: 45565 | H22: 813211 | I22: 167901 | J22: 158358 | K22: 326259 | L22: 21219000 | M22: 0.038324662 | N22: 1899400 | O22: 326259 | P22: 0.089514115 | Q22: 0.015375795 | R22: 0.053700457 | T22: #N/A | U22: 0.2964192 | V22: 0.16320163 | W22: 0.33818145 | AK22: 0.047467961 | AL22: 0.39956092 | AM22: 0.030101492 | AN22: 0.39956092 | AO22: 0.017366469 | AP22: 0.39956092
A23: 45535 | B23: 797162 | C23: 148702 | D23: 152107 | G23: 45535 | H23: 797162 | I23: 148702 | J23: 152107 | K23: 300809 | L23: 21138400 | M23: 0.037711558 | N23: 1871500 | O23: 300809 | P23: 0.088535556 | Q23: 0.014230453 | R23: 0.051942011 | T23: 0.3419836 | U23: 0.33925256 | V23: 0.18752863 | W23: 0.35974432 | AK23: 0.045533322 | AL23: 0.50084125 | AM23: 0.028284317 | AN23: 0.50084125 | AO23: 0.017249005 | AP23: 0.50084125
A24: 45504 | B24: 810835 | C24: 154951 | D24: 150738 | G24: 45504 | H24: 810835 | I24: 154951 | J24: 150738 | K24: 305689 | L24: 21052400 | M24: 0.038515086 | N24: 1846500 | O24: 305689 | P24: 0.087709715 | Q24: 0.014520387 | R24: 0.053035473 | T24: 0.30543614 | U24: 0.3126173 | V24: 0.15564589 | W24: 0.35428585 | AK24: 0.047351579 | AL24: 0.38437438 | AM24: 0.030052142 | AN24: 0.38437438 | AO24: 0.017299437 | AP24: 0.38437438
A25: 45473 | B25: 809322 | C25: 157240 | D25: 149714 | G25: 45473 | H25: 809322 | I25: 157240 | J25: 149714 | K25: 306954 | L25: 21041500 | M25: 0.038463132 | N25: 1834300 | O25: 306954 | P25: 0.087175344 | Q25: 0.014588028 | R25: 0.053051161 | T25: 0.19559453 | U25: 0.31223518 | V25: 0.15770734 | W25: 0.3530124 | AK25: 0.048506307 | AL25: 0.42622117 | AM25: 0.030337977 | AN25: 0.42622117 | AO25: 0.01816833 | AP25: 0.42622117
A26: 45443 | B26: 809431 | C26: 155256 | D26: 145072 | G26: 45443 | H26: 809431 | I26: 155256 | J26: 145072 | K26: 300328 | L26: 20937600 | M26: 0.038659206 | N26: 1818500 | O26: 300328 | P26: 0.086853317 | Q26: 0.014343955 | R26: 0.053003162 | T26: 0.3034329 | U26: 0.31340437 | V26: 0.14992743 | W26: 0.35760745 | AK26: 0.049307162 | AL26: 0.52288302 | AM26: 0.0308738 | AN26: 0.52288302 | AO26: 0.018433362 | AP26: 0.52288302
A27: 45412 | B27: 775464 | C27: 161749 | D27: 149855 | G27: 45412 | H27: 775464 | I27: 161749 | J27: 149855 | K27: 311604 | L27: 21069300 | M27: 0.036805399 | N27: 1795500 | O27: 311604 | P27: 0.085218778 | Q27: 0.01478948 | R27: 0.05159488 | T27: 0.37797002 | U27: 0.3477082 | V27: 0.22348359 | W27: 0.34921975 | AK27: 0.050495858 | AL27: 0.33438932 | AM27: 0.031864414 | AN27: 0.33438932 | AO27: 0.018631444 | AP27: 0.33438932
A28: 45382 | B28: 784136 | C28: 166990 | D28: 151339 | G28: 45382 | H28: 784136 | I28: 166990 | J28: 151339 | K28: 318329 | L28: 21088800 | M28: 0.03718258 | N28: 1804100 | O28: 318329 | P28: 0.085547779 | Q28: 0.015094695 | R28: 0.052277275 | T28: 0.30282525 | U28: 0.33108598 | V28: 0.20851763 | W28: 0.34347361 | AK28: 0.05118036 | AL28: 0.21920976 | AM28: 0.032244198 | AN28: 0.21920976 | AO28: 0.018936162 | AP28: 0.21920976
A29: 45351 | B29: 742963 | C29: 166144 | D29: 150620 | G29: 45351 | H29: 742963 | I29: 166144 | J29: 150620 | K29: 316764 | L29: 20844700 | M29: 0.035642777 | N29: 1774700 | O29: 316764 | P29: 0.085139148 | Q29: 0.015196381 | R29: 0.050839158 | T29: 0.34394171 | U29: 0.36611655 | V29: 0.2696146 | W29: 0.34155921 | AK29: 0.051807616 | AL29: 0.38806415 | AM29: 0.031620331 | AN29: 0.38806415 | AO29: 0.020187285 | AP29: 0.38806415
A30: 45322 | B30: 701975 | C30: 165025 | D30: 144941 | G30: 45322 | H30: 701975 | I30: 165025 | J30: 144941 | K30: 309966 | L30: 20873900 | M30: 0.033629317 | N30: 1751000 | O30: 309966 | P30: 0.08388466 | Q30: 0.014849453 | R30: 0.04847877 | T30: 0.41161667 | U30: 0.42361239 | V30: 0.34950555 | W30: 0.34809067 | AK30: 0.054747881 | AL30: 0.23332167 | AM30: 0.03487628 | AN30: 0.23332167 | AO30: 0.019871601 | AP30: 0.23332167
A31: 45291 | B31: 700774 | C31: 161639 | D31: 147019 | G31: 45291 | H31: 700774 | I31: 161639 | J31: 147019 | K31: 308658 | L31: 20907200 | M31: 0.033518309 | N31: 1693700 | O31: 308658 | P31: 0.08101037 | Q31: 0.014763239 | R31: 0.048281549 | T31: 0.40224282 | U31: 0.42841643 | V31: 0.35391016 | W31: 0.34971377 | AK31: 0.055031804 | AL31: 0.17273277 | AM31: 0.035319868 | AN31: 0.17273277 | AO31: 0.019711936 | AP31: 0.17273277
A32: 45260 | B32: 660887 | C32: 171207 | D32: 146319 | G32: 45260 | H32: 660887 | I32: 171207 | J32: 146319 | K32: 317526 | L32: 20750400 | M32: 0.031849362 | N32: 1667100 | O32: 317526 | P32: 0.08034062 | Q32: 0.015302163 | R32: 0.047151525 | T32: 0.41430449 | U32: 0.45594228 | V32: 0.42013138 | W32: 0.3395677 | AG32: out-sample | AK32: 0.05717867 | AL32: 0.052847295 | AM32: 0.036527832 | AN32: 0.052847295 | AO32: 0.020650837 | AP32: 0.052847295
A33: 45230 | B33: 635276 | C33: 162865 | D33: 142117 | G33: 45230 | H33: 635276 | I33: 162865 | J33: 142117 | K33: 304982 | L33: 20675400 | M33: 0.030726177 | N33: 1623000 | O33: 304982 | P33: 0.078499086 | Q33: 0.01475096 | R33: 0.045477137 | T33: 0.5116101 | U33: 0.49672808 | V33: 0.4646976 | W33: 0.34994495 | AG33: Avg R-Sq | AK33: 0.059263148 | AL33: 0.044321565 | AM33: 0.038635228 | AN33: 0.044321565 | AO33: 0.02062792 | AP33: 0.044321565
A34: 45199 | B34: 680846 | C34: 153918 | D34: 141751 | G34: 45199 | H34: 680846 | I34: 153918 | J34: 141751 | K34: 295669 | L34: 20710000 | M34: 0.032875229 | N34: 1570900 | O34: 295669 | P34: 0.075852245 | Q34: 0.01427663 | R34: 0.047151859 | T34: 0.44703315 | U34: 0.45593414 | V34: 0.37942657 | W34: 0.35887496 | AF34: D+C | AG34: {=AVERAGE(_xlfn.IFNA(_xlfn.ANCHORARRAY('R-Sq'!S3), ""))} -> 0.39030188 | AK34: 0.058701305 | AL34: -0.071253782 | AM34: 0.038288759 | AN34: -0.071253782 | AO34: 0.020412546 | AP34: -0.071253782
A35: 45169 | B35: 689185 | C35: 177711 | D35: 145989 | G35: 45169 | H35: 689185 | I35: 177711 | J35: 145989 | K35: 323700 | L35: 20726900 | M35: 0.033250751 | N35: 1540200 | O35: 323700 | P35: 0.074309231 | Q35: 0.015617386 | R35: 0.048868138 | T35: 0.31147641 | U35: 0.41412793 | V35: 0.36452644 | W35: 0.33363313 | AF35: D | AG35: {=AVERAGE(_xlfn.IFNA(_xlfn.ANCHORARRAY('R-Sq'!T3), ""))} -> 0.44091366 | AK35: 0.063446552 | AL35: -0.10031731 | AM35: 0.04197359 | AN35: -0.10031731 | AO35: 0.021472962 | AP35: -0.10031731
A36: 45138 | B36: 709834 | C36: 174804 | D36: 147921 | G36: 45138 | H36: 709834 | I36: 174804 | J36: 147921 | K36: 322725 | L36: 20751300 | M36: 0.034206724 | N36: 1499000 | O36: 322725 | P36: 0.072236438 | Q36: 0.015552038 | R36: 0.049758762 | T36: 0.21357783 | U36: 0.39243353 | V36: 0.32659493 | W36: 0.33486341 | AF36: C | AG36: {=AVERAGE(_xlfn.IFNA(_xlfn.ANCHORARRAY('R-Sq'!U3), ""))} -> -0.39276309 | AK36: 0.063958484 | AL36: -0.012993178 | AM36: 0.043014788 | AN36: -0.012993178 | AO36: 0.020943696 | AP36: -0.012993178
A37: 45107 | B37: 681228 | C37: 181569 | D37: 145173 | G37: 45107 | H37: 681228 | I37: 181569 | J37: 145173 | K37: 326742 | L37: 20771100 | M37: 0.032796915 | N37: 1469600 | O37: 326742 | P37: 0.070752151 | Q37: 0.015730606 | R37: 0.048527521 | T37: 0.26098226 | U37: 0.42242488 | V37: 0.38253396 | W37: 0.33150158 | AK37: 0.064499086 | AL37: -0.0035653784 | AM37: 0.044300321 | AN37: -0.0035653784 | AO37: 0.020198765 | AP37: -0.0035653784
A38: 45077 | B38: 644170 | C38: 178576 | D38: 147377 | G38: 45077 | H38: 644170 | I38: 178576 | J38: 147377 | K38: 325953 | L38: 20734400 | M38: 0.031067694 | N38: 1444300 | O38: 325953 | P38: 0.069657188 | Q38: 0.015720397 | R38: 0.046788091 | T38: 0.42457944 | U38: 0.46479502 | V38: 0.45114673 | W38: 0.33169379 | AK38: 0.063832142 | AL38: 0.033160422 | AM38: 0.04308641 | AN38: 0.033160422 | AO38: 0.020745732 | AP38: 0.033160422
A39: 45046 | B39: 631949 | C39: 175460 | D39: 145594 | G39: 45046 | H39: 631949 | I39: 175460 | J39: 145594 | K39: 321054 | L39: 20869800 | M39: 0.030280549 | N39: 1392500 | O39: 321054 | P39: 0.066723208 | Q39: 0.015383664 | R39: 0.045664213 | T39: 0.44874896 | U39: 0.49217116 | V39: 0.48237942 | W39: 0.3380333 | AK39: 0.063972243 | AL39: -0.075806841 | AM39: 0.043850631 | AN39: -0.075806841 | AO39: 0.020121612 | AP39: -0.075806841
A40: 45016 | B40: 645429 | C40: 191618 | D40: 152014 | G40: 45016 | H40: 645429 | I40: 191618 | J40: 152014 | K40: 343632 | L40: 21054100 | M40: 0.030655739 | N40: 1369600 | O40: 343632 | P40: 0.065051463 | Q40: 0.016321382 | R40: 0.046977121 | T40: 0.43129377 | U40: 0.46019052 | V40: 0.46749245 | W40: 0.32037931 | AK40: 0.060961114 | AL40: -0.051368929 | AM40: 0.040994761 | AN40: -0.051368929 | AO40: 0.019966353 | AP40: -0.051368929
A41: 44985 | B41: 624379 | C41: 198644 | D41: 159103 | G41: 44985 | H41: 624379 | I41: 198644 | J41: 159103 | K41: 357747 | L41: 21148000 | M41: 0.029524258 | N41: 1309500 | O41: 357747 | P41: 0.061920749 | Q41: 0.016916351 | R41: 0.046440609 | T41: 0.51943378 | U41: 0.47325922 | V41: 0.51238787 | W41: 0.30917807 | AK41: 0.065709904 | AL41: -0.043790562 | AM41: 0.04315108 | AN41: -0.043790562 | AO41: 0.022558824 | AP41: -0.043790562
A42: 44957 | B42: 641228 | C42: 208720 | D42: 161224 | G42: 44957 | H42: 641228 | I42: 208720 | J42: 161224 | K42: 369944 | L42: 21302200 | M42: 0.030101492 | N42: 1269300 | O42: 369944 | P42: 0.059585395 | Q42: 0.017366469 | R42: 0.047467961 | T42: 0.39956092 | U42: 0.44823432 | V42: 0.48948412 | W42: 0.3007039 | AK42: 0.064450097 | AL42: -0.055650297 | AM42: 0.042391589 | AN42: -0.055650297 | AO42: 0.022058508 | AP42: -0.055650297
A43: 44926 | B43: 606659 | C43: 205902 | D43: 164065 | G43: 44926 | H43: 606659 | I43: 205902 | J43: 164065 | K43: 369967 | L43: 21448600 | M43: 0.028284317 | N43: 1187100 | O43: 369967 | P43: 0.05534627 | Q43: 0.017249005 | R43: 0.045533322 | T43: 0.50084125 | U43: 0.49535951 | V43: 0.56158677 | W43: 0.30291536 | AK43: 0.064030248 | AL43: -0.025009705 | AM43: 0.041776724 | AN43: -0.025009705 | AO43: 0.022253525 | AP43: -0.025009705
A44: 44895 | B44: 643783 | C44: 205158 | D44: 165434 | G44: 44895 | H44: 643783 | I44: 205158 | J44: 165434 | K44: 370592 | L44: 21422200 | M44: 0.030052142 | N44: 1143100 | O44: 370592 | P44: 0.053360533 | Q44: 0.017299437 | R44: 0.047351579 | T44: 0.38437438 | U44: 0.45106923 | V44: 0.49144224 | W44: 0.30196589 | AK44: 0.064085034 | AL44: -0.033575029 | AM44: 0.04120708 | AN44: -0.033575029 | AO44: 0.022877954 | AP44: -0.033575029
A45: 44865 | B45: 649618 | C45: 216057 | D45: 172976 | G45: 44865 | H45: 649618 | I45: 216057 | J45: 172976 | K45: 389033 | L45: 21412700 | M45: 0.030337977 | N45: 1112300 | O45: 389033 | P45: 0.051945808 | Q45: 0.01816833 | R45: 0.048506307 | T45: 0.42622117 | U45: 0.42294163 | V45: 0.48010076 | W45: 0.28560762 | AK45: 0.065233125 | AL45: 0.07057193 | AM45: 0.041630469 | AN45: 0.07057193 | AO45: 0.023602656 | AP45: 0.07057193
A46: 44834 | B46: 664009 | C46: 223400 | D46: 173050 | G46: 44834 | H46: 664009 | I46: 223400 | J46: 173050 | K46: 396450 | L46: 21507200 | M46: 0.0308738 | N46: 1061500 | O46: 396450 | P46: 0.049355565 | Q46: 0.018433362 | R46: 0.049307162 | T46: 0.52288302 | U46: 0.40343389 | V46: 0.45884013 | W46: 0.28061798 | AK46: 0.065151467 | AL46: 0.042468982 | AM46: 0.04116457 | AN46: 0.042468982 | AO46: 0.023986897 | AP46: 0.042468982
A47: 44804 | B47: 687787 | C47: 226182 | D47: 175974 | G47: 44804 | H47: 687787 | I47: 226182 | J47: 175974 | K47: 402156 | L47: 21584800 | M47: 0.031864414 | N47: 1034600 | O47: 402156 | P47: 0.047931878 | Q47: 0.018631444 | R47: 0.050495858 | T47: 0.33438932 | U47: 0.37447887 | V47: 0.41953414 | W47: 0.27688877 | AK47: 0.063806829 | AL47: -0.045379865 | AM47: 0.040356081 | AN47: -0.045379865 | AO47: 0.023450748 | AP47: -0.045379865
A48: 44773 | B48: 696781 | C48: 232147 | D48: 177054 | G48: 44773 | H48: 696781 | I48: 232147 | J48: 177054 | K48: 409201 | L48: 21609500 | M48: 0.032244198 | N48: 1024000 | O48: 409201 | P48: 0.047386566 | Q48: 0.018936162 | R48: 0.05118036 | T48: 0.21920976 | U48: 0.35780533 | V48: 0.4044649 | W48: 0.27115197 | AK48: 0.06018322 | AL48: 0.092049748 | AM48: 0.03797543 | AN48: 0.092049748 | AO48: 0.022207789 | AP48: 0.092049748
... A62: 44347 | B62: 861626 | C62: 213356 | D62: 234992 | G62: 44347 | H62: 861626 | I62: 213356 | J62: 234992 | K62: 448348 | L62: 20325400 | M62: 0.042391589 | N62: 988700 | O62: 448348 | P62: 0.048643569 | Q62: 0.022058508 | R62: 0.064450097 | T62: -0.055650297 | U62: 0.034572612 | V62: 0.0018323443 | W62: 0.21236893 | AK62: 0.059483338 | AL62: 0.44369344 | AM62: 0.036969721 | AN62: 0.44369344 | AO62: 0.022513617 | AP62: 0.44369344
A63: 44316 | B63: 847186 | C63: 218132 | D63: 233145 | G63: 44316 | H63: 847186 | I63: 218132 | J63: 233145 | K63: 451277 | L63: 20278900 | M63: 0.041776724 | N63: 1012500 | O63: 451277 | P63: 0.049928744 | Q63: 0.022253525 | R63: 0.064030248 | T63: -0.025009705 | U63: 0.044799555 | V63: 0.026229234 | W63: 0.20869744
A64: 44286 | B64: 822551 | C64: 219522 | D64: 237154 | G64: 44286 | H64: 822551 | I64: 219522 | J64: 237154 | K64: 456676 | L64: 19961400 | M64: 0.04120708 | N64: 1038000 | O64: 456676 | P64: 0.052000361 | Q64: 0.022877954 | R64: 0.064085034 | T64: -0.033575029 | U64: 0.043465045 | V64: 0.048831811 | W64: 0.19694157
A65: 44255 | B65: 813680 | C65: 220840 | D65: 240481 | G65: 44255 | H65: 813680 | I65: 220840 | J65: 240481 | K65: 461321 | L65: 19545300 | M65: 0.041630469 | N65: 1061100 | O65: 461321 | P65: 0.054289266 | Q65: 0.023602656 | R65: 0.065233125 | T65: 0.07057193 | U65: 0.015499111 | V65: 0.032032398 | W65: 0.18329793
A66: 44227 | B66: 798605 | C66: 224133 | D66: 241220 | G66: 44227 | H66: 798605 | I66: 224133 | J66: 241220 | K66: 465353 | L66: 19400300 | M66: 0.04116457 | N66: 1069700 | O66: 465353 | P66: 0.055138323 | Q66: 0.023986897 | R66: 0.065151467 | T66: 0.042468982 | U66: 0.017488198 | V66: 0.050518543 | W66: 0.17606399
A67: 44196 | B67: 778037 | C67: 224987 | D67: 227127 | G67: 44196 | H67: 778037 | I67: 224987 | J67: 227127 | K67: 452114 | L67: 19279300 | M67: 0.040356081 | N67: 1061900 | O67: 452114 | P67: 0.055079801 | Q67: 0.023450748 | R67: 0.063806829 | T67: -0.045379865 | U67: 0.050241741 | V67: 0.082598089 | W67: 0.18615784
A68: 44165 | B68: 722118 | C68: 200723 | D68: 221567 | G68: 44165 | H68: 722118 | I68: 200723 | J68: 221567 | K68: 422290 | L68: 19015400 | M68: 0.03797543 | N68: 1070800 | O68: 422290 | P68: 0.056312252 | Q68: 0.022207789 | R68: 0.06018322 | T68: 0.092049748 | U68: 0.13850793 | V68: 0.17705859 | W68: 0.20955848
A69: 44135 | B69: 659313 | C69: 193293 | D69: 217739 | G69: 44135 | H69: 659313 | I69: 193293 | J69: 217739 | K69: 411032 | L69: 18728000 | M69: 0.035204667 | N69: 1069200 | O69: 411032 | P69: 0.057090987 | Q69: 0.021947458 | R69: 0.057152125 | T69: 0.2631011 | U69: 0.21234127 | V69: 0.28699814 | W69: 0.21445962
A70: 44104 | B70: 654324 | C70: 189462 | D70: 211547 | G70: 44104 | H70: 654324 | I70: 189462 | J70: 211547 | K70: 401009 | L70: 18585200 | M70: 0.035206724 | N70: 1064000 | O70: 401009 | P70: 0.057249855 | Q70: 0.021576792 | R70: 0.056783516 | T70: 0.12559616 | U70: 0.22132009 | V70: 0.28691653 | W70: 0.22143799
A71: 44074 | B71: 645547 | C71: 185113 | D71: 215042 | G71: 44074 | H71: 645547 | I71: 185113 | J71: 215042 | K71: 400155 | L71: 18363900 | M71: 0.035153045 | N71: 1080100 | O71: 400155 | P71: 0.058816482 | Q71: 0.021790306 | R71: 0.056943351 | T71: 0.18050968 | U71: 0.21742673 | V71: 0.28904642 | W71: 0.21741826
A72: 44043 | B72: 613830 | C72: 181420 | D72: 223768 | G72: 44043 | H72: 613830 | I72: 181420 | J72: 223768 | K72: 405188 | L72: 18298300 | M72: 0.033545739 | N72: 1096200 | O72: 405188 | P72: 0.059907204 | Q72: 0.022143478 | R72: 0.055689217 | T72: 0.26315452 | U72: 0.24797572 | V72: 0.35282179 | W72: 0.21076924
A73: 44012 | B73: 584676 | C73: 185497 | D73: 229078 | G73: 44012 | H73: 584676 | I73: 185497 | J73: 229078 | K73: 414575 | L73: 18150000 | M73: 0.032213554 | N73: 1121400 | O73: 414575 | P73: 0.061785124 | Q73: 0.022841598 | R73: 0.055055152 | T73: 0.46128591 | U73: 0.26342069 | V73: 0.40568082 | W73: 0.19762604
A74: 43982 | B74: 552543 | C74: 175794 | D74: 210935 | G74: 43982 | H74: 552543 | I74: 175794 | J74: 210935 | K74: 386729 | L74: 17812800 | M74: 0.031019435 | N74: 1141700 | O74: 386729 | P74: 0.064094359 | Q74: 0.021710736 | R74: 0.052730172 | T74: 0.43675902 | U74: 0.32005404 | V74: 0.45306156 | W74: 0.21891628
... A81: 43769 | B81: 554604 | C81: 145650 | D81: 183966 | G81: 43769 | H81: 554604 | I81: 145650 | J81: 183966 | K81: 329616 | L81: 15162100 | M81: 0.03657831 | N81: 986800 | O81: 329616 | P81: 0.065083333 | Q81: 0.021739469 | R81: 0.058317779 | T81: 0.44697049 | U81: 0.18394752 | V81: 0.23249412 | W81: 0.21837535
A82: 43738 | B82: 555910 | C82: 150648 | D82: 187887 | G82: 43738 | H82: 555910 | I82: 150648 | J82: 187887 | K82: 338535 | L82: 15036900 | M82: 0.036969721 | N82: 959800 | O82: 338535 | P82: 0.063829646 | Q82: 0.022513617 | R82: 0.059483338 | T82: 0.44369344 | U82: #N/A | V82: #N/A | W82: #N/A
A83: 43708 | B83: 564894 | C83: 135567 | D83: 181451 | G83: 43708 | H83: 564894 | I83: 135567 | J83: 181451 | K83: 317018 | L83: 14944200 | M83: 0.037800217 | N83: 936800 | O83: 317018 | P83: 0.062686527 | Q83: 0.021213447 | R83: 0.059013664 | T83: 0.43658547 | U83: #N/A | V83: #N/A | W83: #N/A
A84: 43677 | B84: 602139 | C84: 138703 | D84: 182613 | G84: 43677 | H84: 602139 | I84: 138703 | J84: 182613 | K84: 321316 | L84: 14860700 | M84: 0.040518885 | N84: 922100 | O84: 321316 | P84: 0.062049567 | Q84: 0.021621862 | R84: 0.062140747 | T84: 0.40289832 | U84: #N/A | V84: #N/A | W84: #N/A
A85: 43646 | B85: 596304 | C85: 139826 | D85: 179542 | G85: 43646 | H85: 596304 | I85: 139826 | J85: 179542 | K85: 319368 | L85: 14779300 | M85: 0.040347242 | N85: 896500 | O85: 319368 | P85: 0.060659165 | Q85: 0.021609143 | R85: 0.061956385 | T85: 0.35051462 | U85: #N/A | V85: #N/A | W85: #N/A
A86: 43616 | B86: 568751 | C86: 137489 | D86: 179019 | G86: 43616 | H86: 568751 | I86: 137489 | J86: 179019 | K86: 316508 | L86: 14618100 | M86: 0.038907314 | N86: 894200 | O86: 316508 | P86: 0.06117074 | Q86: 0.021651788 | R86: 0.060559101 | T86: 0.38483529 | U86: #N/A | V86: #N/A | W86: #N/A
A87: 43585 | B87: 588721 | C87: 143802 | D87: 178523 | G87: 43585 | H87: 588721 | I87: 143802 | J87: 178523 | K87: 322325 | L87: 14665000 | M87: 0.04014463 | N87: 880400 | O87: 322325 | P87: 0.060034095 | Q87: 0.021979202 | R87: 0.062123832 | T87: 0.26084665 | U87: #N/A | V87: #N/A | W87: #N/A
A88: 43555 | B88: 574013 | C88: 141074 | D88: 180765 | G88: 43555 | H88: 574013 | I88: 141074 | J88: 180765 | K88: 321839 | L88: 14614300 | M88: 0.039277488 | N88: 892800 | O88: 321839 | P88: 0.061090849 | Q88: 0.022022197 | R88: 0.061299686 | T88: 0.32517295 | U88: #N/A | V88: #N/A | W88: #N/A
A89: 43524 | B89: 581205 | C89: 149686 | D89: 181955 | G89: 43524 | H89: 581205 | I89: 149686 | J89: 181955 | K89: 331641 | L89: 14443200 | M89: 0.040240736 | N89: 882400 | O89: 331641 | P89: 0.061094494 | Q89: 0.02296174 | R89: 0.063202476 | T89: 0.30064389 | U89: #N/A | V89: #N/A | W89: #N/A
A90: 43496 | B90: 568433 | C90: 151804 | D90: 186050 | G90: 43496 | H90: 568433 | I90: 151804 | J90: 186050 | K90: 337854 | L90: 14465200 | M90: 0.039296588 | N90: 873600 | O90: 337854 | P90: 0.06039322 | Q90: 0.023356331 | R90: 0.062652919 | T90: 0.20925995 | U90: #N/A | V90: #N/A | W90: #N/A
A91: 43465 | B91: 554285 | C91: 159572 | D91: 190743 | G91: 43465 | H91: 554285 | I91: 159572 | J91: 190743 | K91: 350315 | L91: 14489000 | M91: 0.038255573 | N91: 855000 | O91: 350315 | P91: 0.059010284 | Q91: 0.024177997 | R91: 0.06243357 | T91: 0.34152417 | U91: #N/A | V91: #N/A | W91: #N/A
A92: 43434 | B92: 592593 | C92: 146452 | D92: 178810 | G92: 43434 | H92: 592593 | I92: 146452 | J92: 178810 | K92: 325262 | L92: 14293500 | M92: 0.041458915 | N92: 803000 | O92: 325262 | P92: 0.056179382 | Q92: 0.022755938 | R92: 0.064214853 | T92: 0.26815021 | U92: #N/A | V92: #N/A | W92: #N/A
A93: 43404 | B93: 607645 | C93: 148037 | D93: 183432 | G93: 43404 | H93: 607645 | I93: 148037 | J93: 183432 | K93: 331469 | L93: 14238800 | M93: 0.042675296 | N93: 787100 | O93: 331469 | P93: 0.055278535 | Q93: 0.023279279 | R93: 0.065954575 | T93: 0.20628089 | U93: #N/A | V93: #N/A | W93: #N/A
... A197: 40237 | B197: 263657 | C197: 106131 | D197: 164624 | G197: 40237 | H197: 263657 | I197: 106131 | J197: 164624 | K197: 270755 | L197: 8528700 | M197: 0.03091409 | N197: 809700 | O197: 270755 | P197: 0.094938267 | Q197: 0.031746339 | R197: 0.062660429 | T197: 0.12899164 | U197: #N/A | V197: #N/A | W197: #N/A
A198: 40209 | B198: 266455 | C198: 281035 | G198: 40209 | H198: 266455 | I198: 281035 | J198: 0 | K198: 281035 | L198: 8484200 | M198: 0.031406025 | N198: 813400 | O198: 281035 | P198: 0.095872327 | Q198: 0.033124514 | R198: 0.064530539 | T198: 0.16708731 | U198: #N/A | V198: #N/A | W198: #N/A
A199: 40178 | B199: 262399 | C199: 281043 | G199: 40178 | H199: 262399 | I199: 281043 | J199: 0 | K199: 281043 | L199: 8560000 | M199: 0.030654089 | N199: 823000 | O199: 281043 | P199: 0.09614486 | Q199: 0.032832126 | R199: 0.063486215 | T199: 0.01463552 | U199: #N/A | V199: #N/A | W199: #N/A
A200: 40147 | B200: 250988 | C200: 284071 | G200: 40147 | H200: 250988 | I200: 284071 | J200: 0 | K200: 284071 | L200: 8517300 | M200: 0.029468024 | N200: 831300 | O200: 284071 | P200: 0.097601353 | Q200: 0.033352236 | R200: 0.06282026 | T200: 0.11250149 | U200: #N/A | V200: #N/A | W200: #N/A
A201: 40117 | B201: 265404 | C201: 299858 | G201: 40117 | H201: 265404 | I201: 299858 | J201: 0 | K201: 299858 | L201: 8443000 | M201: 0.031434798 | N201: 849100 | O201: 299858 | P201: 0.10056852 | Q201: 0.035515575 | R201: 0.066950373 | T201: 0.24714589 | U201: #N/A | V201: #N/A | W201: #N/A
A202: 40086 | B202: 254107 | C202: 287196 | G202: 40086 | H202: 254107 | I202: 287196 | J202: 0 | K202: 287196 | L202: 8412200 | M202: 0.030206961 | N202: 878700 | O202: 287196 | P202: 0.10445543 | Q202: 0.034140415 | R202: 0.064347376 | T202: 0.2493284 | U202: #N/A | V202: #N/A | W202: #N/A
A203: 40056 | B203: 236251 | C203: 281989 | G203: 40056 | H203: 236251 | I203: 281989 | J203: 0 | K203: 281989 | L203: 8404600 | M203: 0.028109726 | N203: 905500 | O203: 281989 | P203: 0.10773862 | Q203: 0.033551745 | R203: 0.061661471 | T203: 0.31802234 | U203: #N/A | V203: #N/A | W203: #N/A
A204: 40025 | B204: 228734 | C204: 277082 | G204: 40025 | H204: 228734 | I204: 277082 | J204: 0 | K204: 277082 | L204: 8425800 | M204: 0.027146858 | N204: 934500 | O204: 277082 | P204: 0.11090935 | Q204: 0.032884949 | R204: 0.060031807 | T204: 0.38089887 | U204: #N/A | V204: #N/A | W204: #N/A
A205: 39994 | B205: 217140 | C205: 283874 | G205: 39994 | H205: 217140 | I205: 283874 | J205: 0 | K205: 283874 | L205: 8459900 | M205: 0.02566697 | N205: 955300 | O205: 283874 | P205: 0.11292096 | Q205: 0.033555243 | R205: 0.059222213 | T205: 0.44218547 | U205: #N/A | V205: #N/A | W205: #N/A
A206: 39964 | B206: 214401 | C206: 275313 | G206: 39964 | H206: 214401 | I206: 275313 | J206: 0 | K206: 275313 | L206: 8446900 | M206: 0.025382211 | N206: 990500 | O206: 275313 | P206: 0.11726195 | Q206: 0.032593377 | R206: 0.057975589 | T206: 0.44398019 | U206: #N/A | V206: #N/A | W206: #N/A
A207: 39933 | B207: 208010 | C207: 285658 | G207: 39933 | H207: 208010 | I207: 285658 | J207: 0 | K207: 285658 | L207: 8459800 | M207: 0.024588052 | N207: 1017800 | O207: 285658 | P207: 0.12031017 | Q207: 0.033766519 | R207: 0.058354571 | T207: 0.47353949 | U207: #N/A | V207: #N/A | W207: #N/A
A208: 39903 | B208: 203967 | C208: 291927 | G208: 39903 | H208: 203967 | I208: 291927 | J208: 0 | K208: 291927 | L208: 8458600 | M208: 0.024113565 | N208: 1052400 | O208: 291927 | P208: 0.12441775 | Q208: 0.034512449 | R208: 0.058626014 | T208: 0.57624678 | U208: #N/A | V208: #N/A | W208: #N/A
A209: 39872 | B209: 199655 | C209: 310503 | G209: 39872 | H209: 199655 | I209: 310503 | J209: 0 | K209: 310503 | L209: 8321600 | M209: 0.023992381 | N209: 1049900 | O209: 310503 | P209: 0.12616564 | Q209: 0.037312897 | R209: 0.061305278 | T209: 0.60599383 | U209: #N/A | V209: #N/A | W209: #N/A
... A354: 35461 | B354: 103337 | C354: 68856 | G354: 35461 | H354: 103337 | I354: 68856 | J354: 0 | K354: 68856 | L354: 3839500 | M354: 0.026914182 | N354: 525700 | O354: 68856 | P354: 0.13691887 | Q354: 0.017933585 | R354: 0.044847767 | T354: 0.3975146 | U354: #N/A | V354: #N/A | W354: #N/A

Sheet SP500_Projection
A1: Mth Fwd | B1: Date | C1: Expected Rtn (Debit + Credit) | D1: Expected Rtn (Debit) | E1: Expected Rtn (Credit) | G1: Ref Date | H1: S&P 500 | I1: Date Projected Lv | J1: Projected Lv (Debit + Credit) | K1: Projected Lv (Debit) | L1: Projected Lv (Credit) | P1: Temp | Q1: Date | R1: R-Sq Wgt Projected Lv | S1: Adj Projected Lv | T1: S&P 500
A2: {=_xlfn.SEQUENCE('Customer Margin Balances'!Z4,,'Customer Margin Balances'!Z4,-1)} -> 24 | B2: {=_xlfn.BYROW(_xlfn.ANCHORARRAY(A2), _xlfn.LAMBDA(_xlpm.mthFwd, EOMONTH('Customer Margin Balances'!G2, _xlpm.mthFwd)))} -> 46904 | C2: {=OFFSET('R-Sq'!K3, 'Customer Margin Balances'!$Z$4, ) *OFFSET('R-Sq'!C3,,,'Customer Margin Balances'!$Z$4) +OFFSET('R-Sq'!O3, 'Customer Margin Balances'!$Z$4, )} -> -0.26858541 | D2: {=OFFSET('R-Sq'!L3, 'Customer Margin Balances'!$Z$4, ) *OFFSET('R-Sq'!D3,,,'Customer Margin Balances'!$Z$4) +OFFSET('R-Sq'!P3, 'Customer Margin Balances'!$Z$4, )} -> -0.68886771 | E2: {=OFFSET('R-Sq'!M3, 'Customer Margin Balances'!$Z$4, ) *OFFSET('R-Sq'!E3,,,'Customer Margin Balances'!$Z$4) +OFFSET('R-Sq'!Q3, 'Customer Margin Balances'!$Z$4, )} -> 0.29563626 | G2: {=EOMONTH(--_xlfn.ANCHORARRAY(B2), -'Customer Margin Balances'!Z2)} -> 46265 | H2: {=INDEX('SP500'!B:B, MATCH(_xlfn.ANCHORARRAY(G2), 'SP500'!A:A, 1))} -> 7354.02 | I2: {=_xlfn.ANCHORARRAY(B2)} -> 46904 | J2: {=_xlfn.ANCHORARRAY($H2) *(1 +_xlfn.ANCHORARRAY(C2))} -> 5378.8376 | K2: {=_xlfn.ANCHORARRAY($H2) *(1 +_xlfn.ANCHORARRAY(D2))} -> 2288.0731 | L2: {=_xlfn.ANCHORARRAY($H2) *(1 +_xlfn.ANCHORARRAY(E2))} -> 9528.135 | Q2: {=_xlfn.LET(_xlpm.sp500_Dt, OFFSET('SP500'!A2,,,COUNT('SP500'!A:A)), _xlfn.VSTACK(_xlfn.ANCHORARRAY(B2), _xlfn._xlws.FILTER(_xlpm.sp500_Dt, _xlpm.sp500_Dt >DATE(1980, 1, 1))))} -> 46904 | R2: {=(_xlfn.ANCHORARRAY(J2) *'Customer Margin Balances'!AE2 +_xlfn.ANCHORARRAY(K2) *'Customer Margin Balances'!AE7 +_xlfn.ANCHORARRAY(L2) *'Customer Margin Balances'!AE12) /SUM('Customer Margin Balances'!AE2, 'Customer Margin Balances'!AE7, 'Customer Margin Balances'!AE12)} -> 4019.0191 | S2: {=_xlfn.ANCHORARRAY(R2) /OFFSET(R2, ROWS(_xlfn.ANCHORARRAY(R2)) -1, ) *OFFSET('SP500'!B1, COUNT('SP500'!B:B), )} -> 4102.9674 | T2: {=_xlfn.LET(_xlpm.sp500_Dt, OFFSET('SP500'!A2,,,COUNT('SP500'!A:A)), _xlpm.sp500_Lv, OFFSET('SP500'!B2,,,ROWS(_xlpm.sp500_Dt)), _xlfn.VSTACK(_xlfn.ANCHORARRAY(S2) *NA(), _xlfn._xlws.FILTER(_xlpm.sp500_Lv, _xlpm.sp500_Dt >=MIN(_xlfn.ANCHORARRAY(Q2)))))} -> #N/A
A3: 23 | B3: 46873 | C3: -0.1733636 | D3: -0.51123676 | E3: 0.28775535 | G3: 46234 | H3: 7354.02 | I3: 46873 | J3: 6079.1006 | K3: 3594.3746 | L3: 9470.1786 | Q3: 46873 | R3: 4989.5156 | S3: 5093.7354 | T3: #N/A
A4: 22 | B4: 46843 | C4: -0.095967205 | D4: -0.38600138 | E4: 0.29054133 | G4: 46203 | H4: 7354.02 | I4: 46843 | J4: 6648.2753 | K4: 4515.3582 | L4: 9490.6668 | Q4: 46843 | R4: 5708.5072 | S4: 5827.7451 | T4: #N/A
A5: 21 | B5: 46812 | C5: -0.12574963 | D5: -0.46466286 | E5: 0.30409961 | G5: 46173 | H5: 7580.0601 | I5: 46812 | J5: 6626.8703 | K5: 4057.8877 | L5: 9885.1533 | Q5: 46812 | R5: 5484.2308 | S5: 5598.7841 | T5: #N/A
A6: 20 | B6: 46783 | C6: -0.15146432 | D6: -0.51371012 | E6: 0.30674542 | G6: 46142 | H6: 7209.0098 | I6: 46783 | J6: 6117.102 | K6: 3505.6685 | L6: 9420.3405 | Q6: 46783 | R6: 4955.0035 | S6: 5058.5024 | T6: #N/A
A7: 19 | B7: 46752 | C7: -0.10701906 | D7: -0.42151398 | E7: 0.29860831 | G7: 46112 | H7: 6528.52 | I7: 46752 | J7: 5829.8439 | K7: 3776.6576 | L7: 8477.9903 | Q7: 46752 | R7: 4919.4856 | S7: 5022.2426 | T7: #N/A
A8: 18 | B8: 46721 | C8: -0.097919969 | D8: -0.42397661 | E8: 0.30718763 | G8: 46081 | H8: 6878.8799 | I8: 46721 | J8: 6205.3002 | K8: 3962.3957 | L8: 8991.9867 | Q8: 46721 | R8: 5203.9228 | S8: 5312.621 | T8: #N/A
A9: 17 | B9: 46691 | C9: -0.070675905 | D9: -0.38061845 | E9: 0.30851669 | G9: 46053 | H9: 6939.0298 | I9: 46691 | J9: 6448.6076 | K9: 4297.907 | L9: 9079.8363 | Q9: 46691 | R9: 5485.7373 | S9: 5600.3221 | T9: #N/A
A10: 16 | B10: 46660 | C10: -0.024110163 | D10: -0.29014816 | E10: 0.30293203 | G10: 46022 | H10: 6845.5 | I10: 46660 | J10: 6680.4539 | K10: 4859.2908 | L10: 8919.2212 | Q10: 46660 | R10: 5865.8136 | S10: 5988.3373 | T10: #N/A
A11: 15 | B11: 46630 | C11: 0.066557557 | D11: -0.18374609 | E11: 0.32554941 | G11: 45991 | H11: 6849.0898 | I11: 46630 | J11: 7304.9485 | K11: 5590.5964 | L11: 9078.807 | Q11: 46630 | R11: 6516.4014 | S11: 6652.5144 | T11: #N/A
A12: 14 | B12: 46599 | C12: 0.087843283 | D12: -0.12605849 | E12: 0.31515453 | G12: 45961 | H12: 6840.2002 | I12: 46599 | J12: 7441.0658 | K12: 5977.9349 | L12: 8995.9202 | Q12: 46599 | R12: 6770.7335 | S12: 6912.1589 | T12: #N/A
A13: 13 | B13: 46568 | C13: 0.094018045 | D13: -0.10576252 | E13: 0.31042908 | G13: 45930 | H13: 6688.46 | I13: 46568 | J13: 7317.2959 | K13: 5981.0716 | L13: 8764.7524 | Q13: 46568 | R13: 6706.891 | S13: 6846.9829 | T13: #N/A
A14: 12 | B14: 46538 | C14: 0.19436892 | D14: 0.031422934 | E14: 0.32613756 | G14: 45900 | H14: 6460.2598 | I14: 46538 | J14: 7715.9335 | K14: 6663.2601 | L14: 8567.1931 | Q14: 46538 | R14: 7216.2697 | S14: 7367.0014 | T14: #N/A
... A25: 1 | B25: 46203 | C25: 0.32748938 | D25: 0.17604958 | E25: 0.36491241 | G25: 45565 | H25: 5762.48 | I25: 46203 | J25: 7649.631 | K25: 6776.9622 | L25: 7865.2804 | Q25: 46203 | R25: 7203.5539 | S25: 7354.02 | T25: #N/A
Q26: 29222 | T26: 105.76
Q27: 29223 | T27: 105.22
Q28: 29224 | T28: 106.52
Q29: 29227 | T29: 106.81
Q30: 29228 | T30: 108.95
Q31: 29229 | T31: 109.05
Q32: 29230 | T32: 109.89
Q33: 29231 | T33: 109.92
Q34: 29234 | T34: 110.38
Q35: 29235 | T35: 111.14
Q36: 29236 | T36: 111.05
Q37: 29237 | T37: 110.7
... Q11741: 46199 | T11741: 7354.02

Sheet R-Sq
A1: =NA() -> #N/A | B1: Y | C1: X | G1: R-Squared (in-sample) | K1: Slope | O1: Intercept | S1: R-Squared (out-sample) | V1: --> 1 - SUM( ( Y_test - Y_est ) ^2 ) / SUM( ( Y_test - AVG( Y_train ) ) ^2 )
A2: Date | B2: ='Customer Margin Balances'!T1 -> S&P 500 FwdRtn (21M) | C2: Debit+Credit : M2 | D2: Debit : M2 | E2: Credit : M2 | G2: Debit+Credit : M2 | H2: Debit : M2 | I2: Credit : M2 | K2: Debit+Credit : M2 | L2: Debit : M2 | M2: Credit : M2 | O2: Debit+Credit : M2 | P2: Debit : M2 | Q2: Credit : M2 | S2: Debit+Credit : M2 (Out-sample) | T2: Debit : M2 (Out-sample) | U2: Credit : M2 (Out-sample)
A3: {=_xlfn.ANCHORARRAY('Customer Margin Balances'!G2)} -> 46173 | B3: {=_xlfn.VSTACK(_xlfn.ANCHORARRAY('Customer Margin Balances'!T2), A1)} -> #N/A | C3: {=_xlfn.ANCHORARRAY('Customer Margin Balances'!R2)} -> 0.080073003 | D3: {=_xlfn.ANCHORARRAY('Customer Margin Balances'!M2)} -> 0.061621778 | E3: {=_xlfn.ANCHORARRAY('Customer Margin Balances'!Q2)} -> 0.018451225 | G3: {=_xlfn.BYROW(_xlfn.ANCHORARRAY($B$3), _xlfn.LAMBDA(_xlpm.knownY, RSQ(OFFSET(_xlpm.knownY,,,'Customer Margin Balances'!$Z$3), OFFSET(_xlpm.knownY,,COLUMN(C2) -COLUMN($B2), 'Customer Margin Balances'!$Z$3))))} -> #N/A | H3: {=_xlfn.BYROW(_xlfn.ANCHORARRAY($B$3), _xlfn.LAMBDA(_xlpm.knownY, RSQ(OFFSET(_xlpm.knownY,,,'Customer Margin Balances'!$Z$3), OFFSET(_xlpm.knownY,,COLUMN(D2) -COLUMN($B2), 'Customer Margin Balances'!$Z$3))))} -> #N/A | I3: {=_xlfn.BYROW(_xlfn.ANCHORARRAY($B$3), _xlfn.LAMBDA(_xlpm.knownY, RSQ(OFFSET(_xlpm.knownY,,,'Customer Margin Balances'!$Z$3), OFFSET(_xlpm.knownY,,COLUMN(E2) -COLUMN($B2), 'Customer Margin Balances'!$Z$3))))} -> #N/A | K3: {=_xlfn.BYROW(_xlfn.ANCHORARRAY($B$3), _xlfn.LAMBDA(_xlpm.knownY, SLOPE(OFFSET(_xlpm.knownY,,,'Customer Margin Balances'!$Z$3), OFFSET(_xlpm.knownY,,COLUMN(C2) -COLUMN($B2), 'Customer Margin Balances'!$Z$3))))} -> #N/A | L3: {=_xlfn.BYROW(_xlfn.ANCHORARRAY($B$3), _xlfn.LAMBDA(_xlpm.knownY, SLOPE(OFFSET(_xlpm.knownY,,,'Customer Margin Balances'!$Z$3), OFFSET(_xlpm.knownY,,COLUMN(D2) -COLUMN($B2), 'Customer Margin Balances'!$Z$3))))} -> #N/A | M3: {=_xlfn.BYROW(_xlfn.ANCHORARRAY($B$3), _xlfn.LAMBDA(_xlpm.knownY, SLOPE(OFFSET(_xlpm.knownY,,,'Customer Margin Balances'!$Z$3), OFFSET(_xlpm.knownY,,COLUMN(E2) -COLUMN($B2), 'Customer Margin Balances'!$Z$3))))} -> #N/A | O3: {=_xlfn.BYROW(_xlfn.ANCHORARRAY($B$3), _xlfn.LAMBDA(_xlpm.knownY, INTERCEPT(OFFSET(_xlpm.knownY,,,'Customer Margin Balances'!$Z$3), OFFSET(_xlpm.knownY,,COLUMN(C2) -COLUMN($B2), 'Customer Margin Balances'!$Z$3))))} -> #N/A | P3: {=_xlfn.BYROW(_xlfn.ANCHORARRAY($B$3), _xlfn.LAMBDA(_xlpm.knownY, INTERCEPT(OFFSET(_xlpm.knownY,,,'Customer Margin Balances'!$Z$3), OFFSET(_xlpm.knownY,,COLUMN(D2) -COLUMN($B2), 'Customer Margin Balances'!$Z$3))))} -> #N/A | Q3: {=_xlfn.BYROW(_xlfn.ANCHORARRAY($B$3), _xlfn.LAMBDA(_xlpm.knownY, INTERCEPT(OFFSET(_xlpm.knownY,,,'Customer Margin Balances'!$Z$3), OFFSET(_xlpm.knownY,,COLUMN(E2) -COLUMN($B2), 'Customer Margin Balances'!$Z$3))))} -> #N/A | S3: {=IFERROR(_xlfn.BYROW(_xlfn.ANCHORARRAY($B3), _xlfn.LAMBDA(_xlpm.knownY, 1 -SUM((OFFSET(_xlpm.knownY,,COLUMN(K2) -COLUMN($B2)) *OFFSET(_xlpm.knownY, -1, COLUMN(C2)-COLUMN($B2), -'Customer Margin Balances'!$Z$4) +OFFSET(_xlpm.knownY,,COLUMN(O2) -COLUMN($B2)) -OFFSET(_xlpm.knownY, -1,, -'Customer Margin Balances'!$Z$4))^2) /SUM((OFFSET(_xlpm.knownY, -1,, -'Customer Margin Balances'!$Z$4) -AVERAGE(OFFSET(_xlpm.knownY,,, 'Customer Margin Balances'!$Z$3)))^2) )), NA())} -> #N/A | T3: {=IFERROR(_xlfn.BYROW(_xlfn.ANCHORARRAY($B3), _xlfn.LAMBDA(_xlpm.knownY, 1 -SUM((OFFSET(_xlpm.knownY,,COLUMN(L2) -COLUMN($B2)) *OFFSET(_xlpm.knownY, -1, COLUMN(D2)-COLUMN($B2), -'Customer Margin Balances'!$Z$4) +OFFSET(_xlpm.knownY,,COLUMN(P2) -COLUMN($B2)) -OFFSET(_xlpm.knownY, -1,, -'Customer Margin Balances'!$Z$4))^2) /SUM((OFFSET(_xlpm.knownY, -1,, -'Customer Margin Balances'!$Z$4) -AVERAGE(OFFSET(_xlpm.knownY,,, 'Customer Margin Balances'!$Z$3)))^2) )), NA())} -> #N/A | U3: {=IFERROR(_xlfn.BYROW(_xlfn.ANCHORARRAY($B3), _xlfn.LAMBDA(_xlpm.knownY, 1 -SUM((OFFSET(_xlpm.knownY,,COLUMN(M2) -COLUMN($B2)) *OFFSET(_xlpm.knownY, -1, COLUMN(E2)-COLUMN($B2), -'Customer Margin Balances'!$Z$4) +OFFSET(_xlpm.knownY,,COLUMN(Q2) -COLUMN($B2)) -OFFSET(_xlpm.knownY, -1,, -'Customer Margin Balances'!$Z$4))^2) /SUM((OFFSET(_xlpm.knownY, -1,, -'Customer Margin Balances'!$Z$4) -AVERAGE(OFFSET(_xlpm.knownY,,, 'Customer Margin Balances'!$Z$3)))^2) )), NA())} -> #N/A
A4: 46142 | B4: #N/A | C4: 0.075756315 | D4: 0.05686561 | E4: 0.018890706 | G4: #N/A | H4: #N/A | I4: #N/A | K4: #N/A | L4: #N/A | M4: #N/A | O4: #N/A | P4: #N/A | Q4: #N/A | S4: #N/A | T4: #N/A | U4: #N/A
A5: 46112 | B5: #N/A | C5: 0.072247707 | D5: 0.053512362 | E5: 0.018735345 | G5: #N/A | H5: #N/A | I5: #N/A | K5: #N/A | L5: #N/A | M5: #N/A | O5: #N/A | P5: #N/A | Q5: #N/A | S5: #N/A | T5: #N/A | U5: #N/A
A6: 46081 | B6: #N/A | C6: 0.073597832 | D6: 0.055618567 | E6: 0.017979265 | G6: #N/A | H6: #N/A | I6: #N/A | K6: #N/A | L6: #N/A | M6: #N/A | O6: #N/A | P6: #N/A | Q6: #N/A | S6: #N/A | T6: #N/A | U6: #N/A
A7: 46053 | B7: #N/A | C7: 0.074763556 | D7: 0.056931835 | E7: 0.017831721 | G7: #N/A | H7: #N/A | I7: #N/A | K7: #N/A | L7: #N/A | M7: #N/A | O7: #N/A | P7: #N/A | Q7: #N/A | S7: #N/A | T7: #N/A | U7: #N/A
A8: 46022 | B8: #N/A | C8: 0.07274872 | D8: 0.054463232 | E8: 0.018285488 | G8: #N/A | H8: #N/A | I8: #N/A | K8: #N/A | L8: #N/A | M8: #N/A | O8: #N/A | P8: #N/A | Q8: #N/A | S8: #N/A | T8: #N/A | U8: #N/A
A9: 45991 | B9: #N/A | C9: 0.072336231 | D9: 0.05452917 | E9: 0.017807061 | G9: #N/A | H9: #N/A | I9: #N/A | K9: #N/A | L9: #N/A | M9: #N/A | O9: #N/A | P9: #N/A | Q9: #N/A | S9: #N/A | T9: #N/A | U9: #N/A
A10: 45961 | B10: #N/A | C10: 0.071101177 | D10: 0.053368231 | E10: 0.017732946 | G10: #N/A | H10: #N/A | I10: #N/A | K10: #N/A | L10: #N/A | M10: #N/A | O10: #N/A | P10: #N/A | Q10: #N/A | S10: #N/A | T10: #N/A | U10: #N/A
A11: 45930 | B11: #N/A | C11: 0.068990213 | D11: 0.050945838 | E11: 0.018044375 | G11: #N/A | H11: #N/A | I11: #N/A | K11: #N/A | L11: #N/A | M11: #N/A | O11: #N/A | P11: #N/A | Q11: #N/A | S11: #N/A | T11: #N/A | U11: #N/A
A12: 45900 | B12: #N/A | C12: 0.064879976 | D12: 0.048096863 | E12: 0.016783113 | G12: #N/A | H12: #N/A | I12: #N/A | K12: #N/A | L12: #N/A | M12: #N/A | O12: #N/A | P12: #N/A | Q12: #N/A | S12: #N/A | T12: #N/A | U12: #N/A
A13: 45869 | B13: #N/A | C13: 0.063915031 | D13: 0.046552245 | E13: 0.017362785 | G13: #N/A | H13: #N/A | I13: #N/A | K13: #N/A | L13: #N/A | M13: #N/A | O13: #N/A | P13: #N/A | Q13: #N/A | S13: #N/A | T13: #N/A | U13: #N/A
A14: 45838 | B14: #N/A | C14: 0.06363511 | D14: 0.04600881 | E14: 0.017626301 | G14: #N/A | H14: #N/A | I14: #N/A | K14: #N/A | L14: #N/A | M14: #N/A | O14: #N/A | P14: #N/A | Q14: #N/A | S14: #N/A | T14: #N/A | U14: #N/A
A15: 45808 | B15: #N/A | C15: 0.059085907 | D15: 0.042335592 | E15: 0.016750315 | G15: #N/A | H15: #N/A | I15: #N/A | K15: #N/A | L15: #N/A | M15: #N/A | O15: #N/A | P15: #N/A | Q15: #N/A | S15: #N/A | T15: #N/A | U15: #N/A
... A23: 45565 | B23: #N/A | C23: 0.053700457 | D23: 0.038324662 | E23: 0.015375795 | G23: #N/A | H23: #N/A | I23: #N/A | K23: #N/A | L23: #N/A | M23: #N/A | O23: #N/A | P23: #N/A | Q23: #N/A | S23: #N/A | T23: #N/A | U23: #N/A
A24: 45535 | B24: 0.3419836 | C24: 0.051942011 | D24: 0.037711558 | E24: 0.014230453 | G24: 0.50681081 | H24: 0.67247784 | I24: 0.074461798 | K24: -23.810905 | L24: -39.435984 | M24: -17.593165 | O24: 1.5791493 | P24: 1.6789735 | Q24: 0.60788215 | S24: #N/A | T24: #N/A | U24: #N/A
A25: 45504 | B25: 0.30543614 | C25: 0.053035473 | D25: 0.038515086 | E25: 0.014520387 | G25: 0.48554487 | H25: 0.66056826 | I25: 0.067406814 | K25: -23.379111 | L25: -39.247612 | M25: -17.119052 | O25: 1.5597195 | P25: 1.6738723 | Q25: 0.60231378 | S25: #N/A | T25: #N/A | U25: #N/A
A26: 45473 | B26: 0.19559453 | C26: 0.053051161 | D26: 0.038463132 | E26: 0.014588028 | G26: 0.45703449 | H26: 0.63260708 | I26: 0.063303809 | K26: -22.5459 | L26: -38.273017 | M26: -16.914892 | O26: 1.5188147 | P26: 1.6419237 | Q26: 0.60198169 | S26: #N/A | T26: #N/A | U26: #N/A
A27: 45443 | B27: 0.3034329 | C27: 0.053003162 | D27: 0.038659206 | E27: 0.014343955 | G27: 0.44445977 | H27: 0.6095082 | I27: 0.068658591 | K27: -22.058999 | L27: -37.34749 | M27: -17.932339 | O27: 1.4977449 | P27: 1.612551 | Q27: 0.62650988 | S27: #N/A | T27: #N/A | U27: #N/A
A28: 45412 | B28: 0.37797002 | C28: 0.05159488 | D28: 0.036805399 | E28: 0.01478948 | G28: 0.42896229 | H28: 0.59900344 | I28: 0.066430789 | K28: -21.631394 | L28: -37.078817 | M28: -18.073092 | O28: 1.4781154 | P28: 1.604436 | Q28: 0.63283004 | S28: #N/A | T28: #N/A | U28: #N/A
A29: 45382 | B29: 0.30282525 | C29: 0.052277275 | D29: 0.03718258 | E29: 0.015094695 | G29: 0.42099388 | H29: 0.59679874 | I29: 0.062606957 | K29: -21.278481 | L29: -36.663773 | M29: -17.850241 | O29: 1.4602843 | P29: 1.589654 | Q29: 0.62861647 | S29: #N/A | T29: #N/A | U29: #N/A
A30: 45351 | B30: 0.34394171 | C30: 0.050839158 | D30: 0.035642777 | E30: 0.015196381 | G30: 0.41175393 | H30: 0.58781821 | I30: 0.061546162 | K30: -20.977146 | L30: -36.249616 | M30: -18.033682 | O30: 1.4470117 | P30: 1.5764304 | Q30: 0.63471534 | S30: #N/A | T30: #N/A | U30: #N/A
A31: 45322 | B31: 0.41161667 | C31: 0.04847877 | D31: 0.033629317 | E31: 0.014849453 | G31: 0.3996834 | H31: 0.57620561 | I31: 0.05784089 | K31: -20.547661 | L31: -35.589879 | M31: -17.735128 | O31: 1.4265155 | P31: 1.5547389 | Q31: 0.63032346 | S31: #N/A | T31: #N/A | U31: #N/A
A32: 45291 | B32: 0.40224282 | C32: 0.048281549 | D32: 0.033518309 | E32: 0.014763239 | G32: 0.39448081 | H32: 0.57376308 | I32: 0.053080731 | K32: -20.429601 | L32: -35.340664 | M32: -17.267267 | O32: 1.4213451 | P32: 1.5457337 | Q32: 0.6199899 | S32: #N/A | T32: #N/A | U32: #N/A
A33: 45260 | B33: 0.41430449 | C33: 0.047151525 | D33: 0.031849362 | E33: 0.015302163 | G33: 0.37791978 | H33: 0.56421691 | I33: 0.042306984 | K33: -20.07512 | L33: -34.996272 | M33: -15.651396 | O33: 1.4050957 | P33: 1.5350556 | Q33: 0.58870801 | S33: #N/A | T33: #N/A | U33: #N/A
A34: 45230 | B34: 0.5116101 | C34: 0.045477137 | D34: 0.030726177 | E34: 0.01475096 | G34: 0.36500944 | H34: 0.54817043 | I34: 0.035752645 | K34: -19.79149 | L34: -34.244623 | M34: -14.681261 | O34: 1.3922408 | P34: 1.5109178 | Q34: 0.56829584 | S34: #N/A | T34: #N/A | U34: #N/A
A35: 45199 | B35: 0.44703315 | C35: 0.047151859 | D35: 0.032875229 | E35: 0.01427663 | G35: 0.34550871 | H35: 0.52997709 | I35: 0.024745022 | K35: -19.256019 | L35: -33.207964 | M35: -12.475075 | O35: 1.3632753 | P35: 1.4747812 | Q35: 0.51967865 | S35: #N/A | T35: #N/A | U35: #N/A
... A41: 45016 | B41: 0.43129377 | C41: 0.046977121 | D41: 0.030655739 | E41: 0.016321382 | G41: 0.38662389 | H41: 0.52350955 | I41: 0.025001681 | K41: -20.275553 | L41: -29.840173 | M41: -16.397863 | O41: 1.4380216 | P41: 1.3646982 | Q41: 0.58599348 | S41: #N/A | T41: #N/A | U41: #N/A
A42: 44985 | B42: 0.51943378 | C42: 0.046440609 | D42: 0.029524258 | E42: 0.016916351 | G42: 0.36165017 | H42: 0.49774034 | I42: 0.015334835 | K42: -19.621002 | L42: -28.815787 | M42: -13.235583 | O42: 1.4033708 | P42: 1.3297039 | Q42: 0.5163788 | R42: check | S42: #N/A | T42: #N/A | U42: #N/A
A43: 44957 | B43: 0.39956092 | C43: 0.047467961 | D43: 0.030101492 | E43: 0.017366469 | G43: 0.33283812 | H43: 0.47239031 | I43: 0.0063262933 | K43: -18.729279 | L43: -27.731156 | M43: -8.5912679 | O43: 1.3518374 | P43: 1.2901034 | Q43: 0.41101267 | R43: =R44=S44 -> #N/A | S43: #N/A | T43: #N/A | U43: #N/A
A44: 44926 | B44: 0.50084125 | C44: 0.045533322 | D44: 0.028284317 | E44: 0.017249005 | G44: 0.32838638 | H44: 0.46655154 | I44: 0.0046166118 | K44: -18.594378 | L44: -27.37513 | M44: -7.4748231 | O44: 1.3462598 | P44: 1.2791392 | Q44: 0.38228058 | R44: {=1 -SUM((K44 *C32:C43 +O44 -B32:B43)^2) /SUM((B32:B43 -AVERAGE(B44:B103))^2)} -> 0.77219685 | S44: #N/A | T44: #N/A | U44: #N/A
A45: 44895 | B45: 0.38437438 | C45: 0.047351579 | D45: 0.030052142 | E45: 0.017299437 | G45: 0.30553391 | H45: 0.4477963 | I45: 0.00066354912 | K45: -18.15334 | L45: -26.977153 | M45: -2.8646521 | O45: 1.3208903 | P45: 1.2652205 | Q45: 0.27522769 | S45: #N/A | T45: #N/A | U45: #N/A
A46: 44865 | B46: 0.42622117 | C46: 0.048506307 | D46: 0.030337977 | E46: 0.01816833 | G46: 0.30036203 | H46: 0.44395292 | I46: 2.4587879e-05 | K46: -18.330073 | L46: -27.165232 | M46: -0.56382125 | O46: 1.3342614 | P46: 1.2748114 | Q46: 0.21994142 | S46: #N/A | T46: #N/A | U46: #N/A
A47: 44834 | B47: 0.52288302 | C47: 0.049307162 | D47: 0.0308738 | E47: 0.018433362 | G47: 0.28279236 | H47: 0.43078146 | I47: 0.00090567149 | K47: -18.065217 | L47: -27.06325 | M47: 3.4356424 | O47: 1.3198908 | P47: 1.2725295 | Q47: 0.12631488 | S47: #N/A | T47: #N/A | U47: #N/A
A48: 44804 | B48: 0.33438932 | C48: 0.050495858 | D48: 0.031864414 | E48: 0.018631444 | G48: 0.24967157 | H48: 0.40530985 | I48: 0.0076833838 | K48: -17.001527 | L48: -26.209219 | M48: 9.8611581 | O48: 1.2540923 | P48: 1.2386503 | Q48: -0.024172881 | S48: 0.86119892 | T48: 0.89869883 | U48: -0.6650279
A49: 44773 | B49: 0.21920976 | C49: 0.05118036 | D49: 0.032244198 | E49: 0.018936162 | G49: 0.24653634 | H49: 0.40409974 | I49: 0.01033027 | K49: -17.239429 | L49: -26.588672 | M49: 11.51048 | O49: 1.270656 | P49: 1.2552458 | Q49: -0.066244737 | S49: 0.85343929 | T49: 0.90548069 | U49: -0.78201077
A50: 44742 | B50: 0.38806415 | C50: 0.051807616 | D50: 0.031620331 | E50: 0.020187285 | G50: 0.25268608 | H50: 0.41466283 | I50: 0.011318051 | K50: -17.825141 | L50: -27.434541 | M50: 12.055859 | O50: 1.3123776 | P50: 1.2938022 | Q50: -0.080460117 | S50: 0.79482693 | T50: 0.87221505 | U50: -0.82602788
A51: 44712 | B51: 0.23332167 | C51: 0.054747881 | D51: 0.03487628 | E51: 0.019871601 | G51: 0.2352209 | H51: 0.40385382 | I51: 0.015436816 | K51: -17.415723 | L51: -27.576536 | M51: 13.557753 | O51: 1.2883011 | P51: 1.3011413 | Q51: -0.11966788 | S51: 0.84322247 | T51: 0.87836899 | U51: -0.92241497
A52: 44681 | B52: 0.17273277 | C52: 0.055031804 | D52: 0.035319868 | E52: 0.019711936 | G52: 0.2365666 | H52: 0.40805514 | I52: 0.014839864 | K52: -17.595264 | L52: -27.982613 | M52: 13.045443 | O52: 1.3027911 | P52: 1.3200641 | Q52: -0.11082291 | S52: 0.82400173 | T52: 0.86488767 | U52: -0.873896
A53: 44651 | B53: 0.052847295 | C53: 0.05717867 | D53: 0.036527832 | E53: 0.020650837 | G53: 0.24758073 | H53: 0.42009211 | I53: 0.011655508 | K53: -18.13856 | L53: -28.636337 | M53: 11.421566 | O53: 1.3412112 | P53: 1.3497566 | Q53: -0.075645684 | S53: 0.75989151 | T53: 0.82760471 | U53: -0.74611632
A54: 44620 | B54: 0.044321565 | C54: 0.059263148 | D54: 0.038635228 | E54: 0.02062792 | G54: 0.27622846 | H54: 0.44653373 | I54: 0.0041022376 | K54: -19.152678 | L54: -29.67297 | M54: 6.552505 | O54: 1.4100297 | P54: 1.3950404 | Q54: 0.035839688 | S54: 0.63788594 | T54: 0.73794488 | U54: -0.3865878
A55: 44592 | B55: -0.071253782 | C55: 0.058701305 | D55: 0.038288759 | E55: 0.020412546 | G55: 0.2893356 | H55: 0.46008788 | I55: 0.0017340524 | K55: -19.395237 | L55: -29.992174 | M55: 4.1052789 | O55: 1.4311789 | P55: 1.4120955 | Q55: 0.094029009 | S55: 0.54489182 | T55: 0.66956272 | U55: -0.22612062
A56: 44561 | B56: -0.10031731 | C56: 0.063446552 | D56: 0.04197359 | E56: 0.021472962 | G56: 0.32488239 | H56: 0.49587782 | I56: 5.2906763e-05 | K56: -20.22628 | L56: -30.724505 | M56: 0.68620679 | O56: 1.4924006 | P56: 1.4479949 | Q56: 0.17780963 | S56: 0.30634741 | T56: 0.50590745 | U56: -0.032395383
A57: 44530 | B57: -0.012993178 | C57: 0.063958484 | D57: 0.043014788 | E57: 0.020943696 | G57: 0.33105175 | H57: 0.50754059 | I57: 1.6676061e-05 | K57: -19.962874 | L57: -30.520892 | M57: 0.36320709 | O57: 1.4837338 | P57: 1.4452377 | Q57: 0.19201829 | S57: 0.19559804 | T57: 0.42173751 | U57: -0.014926116
A58: 44500 | B58: -0.0035653784 | C58: 0.064499086 | D58: 0.044300321 | E58: 0.020198765 | G58: 0.32485884 | H58: 0.503299 | I58: 5.6041311e-07 | K58: -19.513359 | L58: -30.216046 | M58: 0.064734754 | O58: 1.4618907 | P58: 1.43726 | Q58: 0.20456714 | S58: 0.12970609 | T58: 0.37470768 | U58: -0.0023586832
A59: 44469 | B59: 0.033160422 | C59: 0.063832142 | D59: 0.04308641 | E59: 0.020745732 | G59: 0.31967246 | H59: 0.49654376 | I59: 0.00010012123 | K59: -19.141348 | L59: -29.943199 | M59: -0.85015855 | O59: 1.4444779 | P59: 1.4294484 | Q59: 0.23174585 | S59: 0.0078907275 | T59: 0.30922464 | U59: 0.025533397
... A296: 37256 | B296: -0.13249076 | C296: 0.065409935 | D296: 0.02932835 | E296: 0.036081585 | G296: 0.77936473 | H296: 0.40861868 | I296: 0.81964139 | K296: -18.805009 | L296: -20.560685 | M296: -37.997832 | O296: 1.3015166 | P296: 0.85024906 | Q296: 1.0977589 | S296: 0.78213257 | T296: 0.39400503 | U296: -1.6353333
A297: 37225 | B297: -0.11535385 | C297: 0.064523973 | D297: 0.029572475 | E297: 0.034951498 | G297: #N/A | H297: #N/A | I297: #N/A | K297: #N/A | L297: #N/A | M297: #N/A | O297: #N/A | P297: #N/A | Q297: #N/A | S297: #N/A | T297: #N/A | U297: #N/A
A298: 37195 | B298: -0.065551369 | C298: 0.063692478 | D298: 0.028595263 | E298: 0.035097215 | G298: #N/A | H298: #N/A | I298: #N/A | K298: #N/A | L298: #N/A | M298: #N/A | O298: #N/A | P298: #N/A | Q298: #N/A | S298: #N/A | T298: #N/A | U298: #N/A
A299: 37164 | B299: -0.063826873 | C299: 0.069098123 | D299: 0.029556828 | E299: 0.039541295 | G299: #N/A | H299: #N/A | I299: #N/A | K299: #N/A | L299: #N/A | M299: #N/A | O299: #N/A | P299: #N/A | Q299: #N/A | S299: #N/A | T299: #N/A | U299: #N/A
A300: 37134 | B300: -0.14995848 | C300: 0.068914864 | D300: 0.032364095 | E300: 0.036550768 | G300: #N/A | H300: #N/A | I300: #N/A | K300: #N/A | L300: #N/A | M300: #N/A | O300: #N/A | P300: #N/A | Q300: #N/A | S300: #N/A | T300: #N/A | U300: #N/A
A301: 37103 | B301: -0.24298441 | C301: 0.069053256 | D301: 0.033427642 | E301: 0.035625613 | G301: #N/A | H301: #N/A | I301: #N/A | K301: #N/A | L301: #N/A | M301: #N/A | O301: #N/A | P301: #N/A | Q301: #N/A | S301: #N/A | T301: #N/A | U301: #N/A
A302: 37072 | B302: -0.30725756 | C302: 0.071062492 | D302: 0.034755472 | E302: 0.036307019 | G302: #N/A | H302: #N/A | I302: #N/A | K302: #N/A | L302: #N/A | M302: #N/A | O302: #N/A | P302: #N/A | Q302: #N/A | S302: #N/A | T302: #N/A | U302: #N/A
A303: 37042 | B303: -0.33019855 | C303: 0.071653048 | D303: 0.035782344 | E303: 0.035870704 | G303: #N/A | H303: #N/A | I303: #N/A | K303: #N/A | L303: #N/A | M303: #N/A | O303: #N/A | P303: #N/A | Q303: #N/A | S303: #N/A | T303: #N/A | U303: #N/A
A304: 37011 | B304: -0.31514411 | C304: 0.070931549 | D304: 0.034012439 | E304: 0.03691911 | G304: #N/A | H304: #N/A | I304: #N/A | K304: #N/A | L304: #N/A | M304: #N/A | O304: #N/A | P304: #N/A | Q304: #N/A | S304: #N/A | T304: #N/A | U304: #N/A
A305: 36981 | B305: -0.24175016 | C305: 0.07319415 | D305: 0.034265859 | E305: 0.038928291 | G305: #N/A | H305: #N/A | I305: #N/A | K305: #N/A | L305: #N/A | M305: #N/A | O305: #N/A | P305: #N/A | Q305: #N/A | S305: #N/A | T305: #N/A | U305: #N/A
A306: 36950 | B306: -0.24487472 | C306: 0.078259993 | D306: 0.039690874 | E306: 0.038569119 | G306: #N/A | H306: #N/A | I306: #N/A | K306: #N/A | L306: #N/A | M306: #N/A | O306: #N/A | P306: #N/A | Q306: #N/A | S306: #N/A | T306: #N/A | U306: #N/A
A307: 36922 | B307: -0.35157136 | C307: 0.079474868 | D307: 0.041891561 | E307: 0.037583307 | G307: #N/A | H307: #N/A | I307: #N/A | K307: #N/A | L307: #N/A | M307: #N/A | O307: #N/A | P307: #N/A | Q307: #N/A | S307: #N/A | T307: #N/A | U307: #N/A
A308: 36891 | B308: -0.38249461 | C308: 0.082446575 | D308: 0.042454848 | E308: 0.039991726 | G308: #N/A | H308: #N/A | I308: #N/A | K308: #N/A | L308: #N/A | M308: #N/A | O308: #N/A | P308: #N/A | Q308: #N/A | S308: #N/A | T308: #N/A | U308: #N/A
... A355: 35461 | B355: 0.3975146 | C355: 0.044847767 | D355: 0.026914182 | E355: 0.017933585 | G355: #N/A | H355: #N/A | I355: #N/A | K355: #N/A | L355: #N/A | M355: #N/A | O355: #N/A | P355: #N/A | Q355: #N/A | S355: #N/A | T355: #N/A | U355: #N/A
B356: #N/A | G356: #N/A | H356: #N/A | I356: #N/A | K356: #N/A | L356: #N/A | M356: #N/A | O356: #N/A | P356: #N/A | Q356: #N/A | S356: #N/A | T356: #N/A | U356: #N/A

Sheet USM2(NS)
A1: observation_date | B1: M2NS
A2: {=OFFSET(FRED_RawData!A8,,,COUNTA(FRED_RawData!A:A)-COUNTA(FRED_RawData!A1:A7), 2)} -> 21551 | B2: 289.8
A3: 21582 | B3: 287.7
A4: 21610 | B4: 287.9
A5: 21641 | B5: 290.2
A6: 21671 | B6: 290.2
A7: 21702 | B7: 292.5
A8: 21732 | B8: 294.4
A9: 21763 | B9: 294.8
A10: 21794 | B10: 296.1
A11: 21824 | B11: 296.9
A12: 21855 | B12: 297.8
A13: 21885 | B13: 300.6
A14: 21916 | B14: 301.5
... A810: 46143 | B810: 22971.7

Sheet MMF
A1: observation_date | B1: WRMFNS
A2: {=OFFSET(FRED_RawData!C8,,,COUNTA(FRED_RawData!C:C)-COUNTA(FRED_RawData!C1:C7), 2)} -> 29255 | B2: 41.9
A3: 29262 | B3: 41.9
A4: 29269 | B4: 43.2
A5: 29276 | B5: 44.4
A6: 29283 | B6: 45.9
A7: 29290 | B7: 46.7
A8: 29297 | B8: 47.2
A9: 29304 | B9: 47.6
A10: 29311 | B10: 47.4
A11: 29318 | B11: 46.9
A12: 29325 | B12: 46.9
A13: 29332 | B13: 46.6
A14: 29339 | B14: 46.7
... A2419: 46174 | B2419: 2274.7

Sheet SP500

Sheet FRED_RawData
A1: M2NS | C1: WRMFNS
A2: lin | B2: Billions of Dollars, Not Seasonally Adjusted | C2: lin | D2: Billions of Dollars, Not Seasonally Adjusted
A3: m | B3: Monthly | C3: w | D3: Weekly, Ending Monday
A4: 21551 | B4: 1959-01-01 to 2026-05-01 | C4: 29255 | D4: 1980-02-04 to 2026-06-01
A5: M2 | C5: Retail Money Market Funds
A6: Board of Governors of the Federal Reserve System (US) | C6: Board of Governors of the Federal Reserve System (US)
A7: date | B7: value | C7: date | D7: value
A8: 21551 | B8: 289.8 | C8: 29255 | D8: 41.9
A9: 21582 | B9: 287.7 | C9: 29262 | D9: 41.9
A10: 21610 | B10: 287.9 | C10: 29269 | D10: 43.2
A11: 21641 | B11: 290.2 | C11: 29276 | D11: 44.4
A12: 21671 | B12: 290.2 | C12: 29283 | D12: 45.9
A13: 21702 | B13: 292.5 | C13: 29290 | D13: 46.7
A14: 21732 | B14: 294.4 | C14: 29297 | D14: 47.2
A15: 21763 | B15: 294.8 | C15: 29304 | D15: 47.6
A16: 21794 | B16: 296.1 | C16: 29311 | D16: 47.4
A17: 21824 | B17: 296.9 | C17: 29318 | D17: 46.9
A18: 21855 | B18: 297.8 | C18: 29325 | D18: 46.9
A19: 21885 | B19: 300.6 | C19: 29332 | D19: 46.6
... A816: 46143 | B816: 22971.7 | C816: 34911 | D816: 407.1
C817: 34918 | D817: 411.3
C818: 34925 | D818: 414.3
C819: 34932 | D819: 416.9
C820: 34939 | D820: 418.8
C821: 34946 | D821: 418.2
C822: 34953 | D822: 419.7
C823: 34960 | D823: 419.9
C824: 34967 | D824: 418.1
C825: 34974 | D825: 417.9
C826: 34981 | D826: 422.3
C827: 34988 | D827: 423.7
C828: 34995 | D828: 423.5
... C2425: 46174 | D2425: 2274.7
